[{"zip":"90001","county":"Los Angeles"},{"zip":"90002","county":"Los Angeles"},{"zip":"90003","county":"Los Angeles"},{"zip":"90004","county":"Los Angeles"},{"zip":"90005","county":"Los Angeles"},{"zip":"90006","county":"Los Angeles"},{"zip":"90007","county":"Los Angeles"},{"zip":"90008","county":"Los Angeles"},{"zip":"90009","county":"Los Angeles"},{"zip":"90010","county":"Los Angeles"},{"zip":"90011","county":"Los Angeles"},{"zip":"90012","county":"Los Angeles"},{"zip":"90013","county":"Los Angeles"},{"zip":"90014","county":"Los Angeles"},{"zip":"90015","county":"Los Angeles"},{"zip":"90016","county":"Los Angeles"},{"zip":"90017","county":"Los Angeles"},{"zip":"90018","county":"Los Angeles"},{"zip":"90019","county":"Los Angeles"},{"zip":"90020","county":"Los Angeles"},{"zip":"90021","county":"Los Angeles"},{"zip":"90022","county":"Los Angeles"},{"zip":"90023","county":"Los Angeles"},{"zip":"90024","county":"Los Angeles"},{"zip":"90025","county":"Los Angeles"},{"zip":"90026","county":"Los Angeles"},{"zip":"90027","county":"Los Angeles"},{"zip":"90028","county":"Los Angeles"},{"zip":"90029","county":"Los Angeles"},{"zip":"90030","county":"Los Angeles"},{"zip":"90031","county":"Los Angeles"},{"zip":"90032","county":"Los Angeles"},{"zip":"90033","county":"Los Angeles"},{"zip":"90034","county":"Los Angeles"},{"zip":"90035","county":"Los Angeles"},{"zip":"90036","county":"Los Angeles"},{"zip":"90037","county":"Los Angeles"},{"zip":"90038","county":"Los Angeles"},{"zip":"90039","county":"Los Angeles"},{"zip":"90040","county":"Los Angeles"},{"zip":"90041","county":"Los Angeles"},{"zip":"90042","county":"Los Angeles"},{"zip":"90043","county":"Los Angeles"},{"zip":"90044","county":"Los Angeles"},{"zip":"90045","county":"Los Angeles"},{"zip":"90046","county":"Los Angeles"},{"zip":"90047","county":"Los Angeles"},{"zip":"90048","county":"Los Angeles"},{"zip":"90049","county":"Los Angeles"},{"zip":"90050","county":"Los Angeles"},{"zip":"90051","county":"Los Angeles"},{"zip":"90052","county":"Los Angeles"},{"zip":"90053","county":"Los Angeles"},{"zip":"90054","county":"Los Angeles"},{"zip":"90055","county":"Los Angeles"},{"zip":"90056","county":"Los Angeles"},{"zip":"90057","county":"Los Angeles"},{"zip":"90058","county":"Los Angeles"},{"zip":"90059","county":"Los Angeles"},{"zip":"90060","county":"Los Angeles"},{"zip":"90061","county":"Los Angeles"},{"zip":"90062","county":"Los Angeles"},{"zip":"90063","county":"Los Angeles"},{"zip":"90064","county":"Los Angeles"},{"zip":"90065","county":"Los Angeles"},{"zip":"90066","county":"Los Angeles"},{"zip":"90067","county":"Los Angeles"},{"zip":"90068","county":"Los Angeles"},{"zip":"90069","county":"Los Angeles"},{"zip":"90070","county":"Los Angeles"},{"zip":"90071","county":"Los Angeles"},{"zip":"90072","county":"Los Angeles"},{"zip":"90073","county":"Los Angeles"},{"zip":"90074","county":"Los Angeles"},{"zip":"90075","county":"Los Angeles"},{"zip":"90076","county":"Los Angeles"},{"zip":"90077","county":"Los Angeles"},{"zip":"90078","county":"Los Angeles"},{"zip":"90079","county":"Los Angeles"},{"zip":"90080","county":"Los Angeles"},{"zip":"90081","county":"Los Angeles"},{"zip":"90082","county":"Los Angeles"},{"zip":"90083","county":"Los Angeles"},{"zip":"90084","county":"Los Angeles"},{"zip":"90086","county":"Los Angeles"},{"zip":"90087","county":"Los Angeles"},{"zip":"90088","county":"Los Angeles"},{"zip":"90089","county":"Los Angeles"},{"zip":"90091","county":"Los Angeles"},{"zip":"90093","county":"Los Angeles"},{"zip":"90094","county":"Los Angeles"},{"zip":"90095","county":"Los Angeles"},{"zip":"90096","county":"Los Angeles"},{"zip":"90099","county":"Los Angeles"},{"zip":"90101","county":"Los Angeles"},{"zip":"90102","county":"Los Angeles"},{"zip":"90103","county":"Los Angeles"},{"zip":"90189","county":"Los Angeles"},{"zip":"90201","county":"Los Angeles"},{"zip":"90202","county":"Los Angeles"},{"zip":"90209","county":"Los Angeles"},{"zip":"90210","county":"Los Angeles"},{"zip":"90211","county":"Los Angeles"},{"zip":"90212","county":"Los Angeles"},{"zip":"90213","county":"Los Angeles"},{"zip":"90220","county":"Los Angeles"},{"zip":"90221","county":"Los Angeles"},{"zip":"90222","county":"Los Angeles"},{"zip":"90223","county":"Los Angeles"},{"zip":"90224","county":"Los Angeles"},{"zip":"90230","county":"Los Angeles"},{"zip":"90231","county":"Los Angeles"},{"zip":"90232","county":"Los Angeles"},{"zip":"90233","county":"Los Angeles"},{"zip":"90239","county":"Los Angeles"},{"zip":"90240","county":"Los Angeles"},{"zip":"90241","county":"Los Angeles"},{"zip":"90242","county":"Los Angeles"},{"zip":"90245","county":"Los Angeles"},{"zip":"90247","county":"Los Angeles"},{"zip":"90248","county":"Los Angeles"},{"zip":"90249","county":"Los Angeles"},{"zip":"90250","county":"Los Angeles"},{"zip":"90251","county":"Los Angeles"},{"zip":"90254","county":"Los Angeles"},{"zip":"90255","county":"Los Angeles"},{"zip":"90260","county":"Los Angeles"},{"zip":"90261","county":"Los Angeles"},{"zip":"90262","county":"Los Angeles"},{"zip":"90263","county":"Los Angeles"},{"zip":"90264","county":"Los Angeles"},{"zip":"90265","county":"Los Angeles"},{"zip":"90266","county":"Los Angeles"},{"zip":"90267","county":"Los Angeles"},{"zip":"90270","county":"Los Angeles"},{"zip":"90272","county":"Los Angeles"},{"zip":"90274","county":"Los Angeles"},{"zip":"90275","county":"Los Angeles"},{"zip":"90277","county":"Los Angeles"},{"zip":"90278","county":"Los Angeles"},{"zip":"90280","county":"Los Angeles"},{"zip":"90290","county":"Los Angeles"},{"zip":"90291","county":"Los Angeles"},{"zip":"90292","county":"Los Angeles"},{"zip":"90293","county":"Los Angeles"},{"zip":"90294","county":"Los Angeles"},{"zip":"90295","county":"Los Angeles"},{"zip":"90296","county":"Los Angeles"},{"zip":"90301","county":"Los Angeles"},{"zip":"90302","county":"Los Angeles"},{"zip":"90303","county":"Los Angeles"},{"zip":"90304","county":"Los Angeles"},{"zip":"90305","county":"Los Angeles"},{"zip":"90306","county":"Los Angeles"},{"zip":"90307","county":"Los Angeles"},{"zip":"90308","county":"Los Angeles"},{"zip":"90309","county":"Los Angeles"},{"zip":"90310","county":"Los Angeles"},{"zip":"90311","county":"Los Angeles"},{"zip":"90312","county":"Los Angeles"},{"zip":"90313","county":"Los Angeles"},{"zip":"90397","county":"Los Angeles"},{"zip":"90398","county":"Los Angeles"},{"zip":"90401","county":"Los Angeles"},{"zip":"90402","county":"Los Angeles"},{"zip":"90403","county":"Los Angeles"},{"zip":"90404","county":"Los Angeles"},{"zip":"90405","county":"Los Angeles"},{"zip":"90406","county":"Los Angeles"},{"zip":"90407","county":"Los Angeles"},{"zip":"90408","county":"Los Angeles"},{"zip":"90409","county":"Los Angeles"},{"zip":"90410","county":"Los Angeles"},{"zip":"90411","county":"Los Angeles"},{"zip":"90501","county":"Los Angeles"},{"zip":"90502","county":"Los Angeles"},{"zip":"90503","county":"Los Angeles"},{"zip":"90504","county":"Los Angeles"},{"zip":"90505","county":"Los Angeles"},{"zip":"90506","county":"Los Angeles"},{"zip":"90507","county":"Los Angeles"},{"zip":"90508","county":"Los Angeles"},{"zip":"90509","county":"Los Angeles"},{"zip":"90510","county":"Los Angeles"},{"zip":"90601","county":"Los Angeles"},{"zip":"90602","county":"Los Angeles"},{"zip":"90603","county":"Los Angeles"},{"zip":"90604","county":"Los Angeles"},{"zip":"90605","county":"Los Angeles"},{"zip":"90606","county":"Los Angeles"},{"zip":"90607","county":"Los Angeles"},{"zip":"90608","county":"Los Angeles"},{"zip":"90609","county":"Los Angeles"},{"zip":"90610","county":"Los Angeles"},{"zip":"90612","county":"Los Angeles"},{"zip":"90620","county":"Orange"},{"zip":"90621","county":"Orange"},{"zip":"90622","county":"Orange"},{"zip":"90623","county":"Orange"},{"zip":"90624","county":"Orange"},{"zip":"90630","county":"Orange"},{"zip":"90631","county":"Orange"},{"zip":"90632","county":"Orange"},{"zip":"90633","county":"Orange"},{"zip":"90637","county":"Los Angeles"},{"zip":"90638","county":"Los Angeles"},{"zip":"90639","county":"Los Angeles"},{"zip":"90640","county":"Los Angeles"},{"zip":"90650","county":"Los Angeles"},{"zip":"90651","county":"Los Angeles"},{"zip":"90652","county":"Los Angeles"},{"zip":"90659","county":"Los Angeles"},{"zip":"90660","county":"Los Angeles"},{"zip":"90661","county":"Los Angeles"},{"zip":"90662","county":"Los Angeles"},{"zip":"90670","county":"Los Angeles"},{"zip":"90671","county":"Los Angeles"},{"zip":"90680","county":"Orange"},{"zip":"90701","county":"Los Angeles"},{"zip":"90702","county":"Los Angeles"},{"zip":"90703","county":"Los Angeles"},{"zip":"90704","county":"Los Angeles"},{"zip":"90706","county":"Los Angeles"},{"zip":"90707","county":"Los Angeles"},{"zip":"90710","county":"Los Angeles"},{"zip":"90711","county":"Los Angeles"},{"zip":"90712","county":"Los Angeles"},{"zip":"90713","county":"Los Angeles"},{"zip":"90714","county":"Los Angeles"},{"zip":"90715","county":"Los Angeles"},{"zip":"90716","county":"Los Angeles"},{"zip":"90717","county":"Los Angeles"},{"zip":"90720","county":"Orange"},{"zip":"90721","county":"Orange"},{"zip":"90723","county":"Los Angeles"},{"zip":"90731","county":"Los Angeles"},{"zip":"90732","county":"Los Angeles"},{"zip":"90733","county":"Los Angeles"},{"zip":"90734","county":"Los Angeles"},{"zip":"90740","county":"Orange"},{"zip":"90742","county":"Orange"},{"zip":"90743","county":"Orange"},{"zip":"90744","county":"Los Angeles"},{"zip":"90745","county":"Los Angeles"},{"zip":"90746","county":"Los Angeles"},{"zip":"90747","county":"Los Angeles"},{"zip":"90748","county":"Los Angeles"},{"zip":"90749","county":"Los Angeles"},{"zip":"90755","county":"Los Angeles"},{"zip":"90801","county":"Los Angeles"},{"zip":"90802","county":"Los Angeles"},{"zip":"90803","county":"Los Angeles"},{"zip":"90804","county":"Los Angeles"},{"zip":"90805","county":"Los Angeles"},{"zip":"90806","county":"Los Angeles"},{"zip":"90807","county":"Los Angeles"},{"zip":"90808","county":"Los Angeles"},{"zip":"90809","county":"Los Angeles"},{"zip":"90810","county":"Los Angeles"},{"zip":"90813","county":"Los Angeles"},{"zip":"90814","county":"Los Angeles"},{"zip":"90815","county":"Los Angeles"},{"zip":"90822","county":"Los Angeles"},{"zip":"90831","county":"Los Angeles"},{"zip":"90832","county":"Los Angeles"},{"zip":"90833","county":"Los Angeles"},{"zip":"90834","county":"Los Angeles"},{"zip":"90835","county":"Los Angeles"},{"zip":"90840","county":"Los Angeles"},{"zip":"90842","county":"Los Angeles"},{"zip":"90844","county":"Los Angeles"},{"zip":"90845","county":"Los Angeles"},{"zip":"90846","county":"Los Angeles"},{"zip":"90847","county":"Los Angeles"},{"zip":"90848","county":"Los Angeles"},{"zip":"90853","county":"Los Angeles"},{"zip":"90888","county":"Los Angeles"},{"zip":"90895","county":"Los Angeles"},{"zip":"90899","county":"Los Angeles"},{"zip":"91001","county":"Los Angeles"},{"zip":"91003","county":"Los Angeles"},{"zip":"91006","county":"Los Angeles"},{"zip":"91007","county":"Los Angeles"},{"zip":"91009","county":"Los Angeles"},{"zip":"91010","county":"Los Angeles"},{"zip":"91011","county":"Los Angeles"},{"zip":"91012","county":"Los Angeles"},{"zip":"91016","county":"Los Angeles"},{"zip":"91017","county":"Los Angeles"},{"zip":"91020","county":"Los Angeles"},{"zip":"91021","county":"Los Angeles"},{"zip":"91023","county":"Los Angeles"},{"zip":"91024","county":"Los Angeles"},{"zip":"91025","county":"Los Angeles"},{"zip":"91030","county":"Los Angeles"},{"zip":"91031","county":"Los Angeles"},{"zip":"91040","county":"Los Angeles"},{"zip":"91041","county":"Los Angeles"},{"zip":"91042","county":"Los Angeles"},{"zip":"91043","county":"Los Angeles"},{"zip":"91046","county":"Los Angeles"},{"zip":"91066","county":"Los Angeles"},{"zip":"91077","county":"Los Angeles"},{"zip":"91101","county":"Los Angeles"},{"zip":"91102","county":"Los Angeles"},{"zip":"91103","county":"Los Angeles"},{"zip":"91104","county":"Los Angeles"},{"zip":"91105","county":"Los Angeles"},{"zip":"91106","county":"Los Angeles"},{"zip":"91107","county":"Los Angeles"},{"zip":"91108","county":"Los Angeles"},{"zip":"91109","county":"Los Angeles"},{"zip":"91110","county":"Los Angeles"},{"zip":"91114","county":"Los Angeles"},{"zip":"91115","county":"Los Angeles"},{"zip":"91116","county":"Los Angeles"},{"zip":"91117","county":"Los Angeles"},{"zip":"91118","county":"Los Angeles"},{"zip":"91121","county":"Los Angeles"},{"zip":"91123","county":"Los Angeles"},{"zip":"91124","county":"Los Angeles"},{"zip":"91125","county":"Los Angeles"},{"zip":"91126","county":"Los Angeles"},{"zip":"91129","county":"Los Angeles"},{"zip":"91131","county":"Los Angeles"},{"zip":"91182","county":"Los Angeles"},{"zip":"91184","county":"Los Angeles"},{"zip":"91185","county":"Los Angeles"},{"zip":"91188","county":"Los Angeles"},{"zip":"91189","county":"Los Angeles"},{"zip":"91191","county":"Los Angeles"},{"zip":"91199","county":"Los Angeles"},{"zip":"91201","county":"Los Angeles"},{"zip":"91202","county":"Los Angeles"},{"zip":"91203","county":"Los Angeles"},{"zip":"91204","county":"Los Angeles"},{"zip":"91205","county":"Los Angeles"},{"zip":"91206","county":"Los Angeles"},{"zip":"91207","county":"Los Angeles"},{"zip":"91208","county":"Los Angeles"},{"zip":"91209","county":"Los Angeles"},{"zip":"91210","county":"Los Angeles"},{"zip":"91214","county":"Los Angeles"},{"zip":"91221","county":"Los Angeles"},{"zip":"91222","county":"Los Angeles"},{"zip":"91224","county":"Los Angeles"},{"zip":"91225","county":"Los Angeles"},{"zip":"91226","county":"Los Angeles"},{"zip":"91301","county":"Los Angeles"},{"zip":"91302","county":"Los Angeles"},{"zip":"91303","county":"Los Angeles"},{"zip":"91304","county":"Los Angeles"},{"zip":"91305","county":"Los Angeles"},{"zip":"91306","county":"Los Angeles"},{"zip":"91307","county":"Los Angeles"},{"zip":"91308","county":"Los Angeles"},{"zip":"91309","county":"Los Angeles"},{"zip":"91310","county":"Los Angeles"},{"zip":"91311","county":"Los Angeles"},{"zip":"91313","county":"Los Angeles"},{"zip":"91316","county":"Los Angeles"},{"zip":"91319","county":"Ventura"},{"zip":"91320","county":"Ventura"},{"zip":"91321","county":"Los Angeles"},{"zip":"91322","county":"Los Angeles"},{"zip":"91324","county":"Los Angeles"},{"zip":"91325","county":"Los Angeles"},{"zip":"91326","county":"Los Angeles"},{"zip":"91327","county":"Los Angeles"},{"zip":"91328","county":"Los Angeles"},{"zip":"91329","county":"Los Angeles"},{"zip":"91330","county":"Los Angeles"},{"zip":"91331","county":"Los Angeles"},{"zip":"91333","county":"Los Angeles"},{"zip":"91334","county":"Los Angeles"},{"zip":"91335","county":"Los Angeles"},{"zip":"91337","county":"Los Angeles"},{"zip":"91340","county":"Los Angeles"},{"zip":"91341","county":"Los Angeles"},{"zip":"91342","county":"Los Angeles"},{"zip":"91343","county":"Los Angeles"},{"zip":"91344","county":"Los Angeles"},{"zip":"91345","county":"Los Angeles"},{"zip":"91346","county":"Los Angeles"},{"zip":"91350","county":"Los Angeles"},{"zip":"91351","county":"Los Angeles"},{"zip":"91352","county":"Los Angeles"},{"zip":"91353","county":"Los Angeles"},{"zip":"91354","county":"Los Angeles"},{"zip":"91355","county":"Los Angeles"},{"zip":"91356","county":"Los Angeles"},{"zip":"91357","county":"Los Angeles"},{"zip":"91358","county":"Ventura"},{"zip":"91359","county":"Ventura"},{"zip":"91360","county":"Ventura"},{"zip":"91361","county":"Ventura"},{"zip":"91362","county":"Ventura"},{"zip":"91363","county":"Los Angeles"},{"zip":"91364","county":"Los Angeles"},{"zip":"91365","county":"Los Angeles"},{"zip":"91367","county":"Los Angeles"},{"zip":"91371","county":"Los Angeles"},{"zip":"91372","county":"Los Angeles"},{"zip":"91376","county":"Los Angeles"},{"zip":"91377","county":"Ventura"},{"zip":"91380","county":"Los Angeles"},{"zip":"91381","county":"Los Angeles"},{"zip":"91382","county":"Los Angeles"},{"zip":"91383","county":"Los Angeles"},{"zip":"91384","county":"Los Angeles"},{"zip":"91385","county":"Los Angeles"},{"zip":"91386","county":"Los Angeles"},{"zip":"91387","county":"Los Angeles"},{"zip":"91388","county":"Los Angeles"},{"zip":"91390","county":"Los Angeles"},{"zip":"91392","county":"Los Angeles"},{"zip":"91393","county":"Los Angeles"},{"zip":"91394","county":"Los Angeles"},{"zip":"91395","county":"Los Angeles"},{"zip":"91396","county":"Los Angeles"},{"zip":"91399","county":"Los Angeles"},{"zip":"91401","county":"Los Angeles"},{"zip":"91402","county":"Los Angeles"},{"zip":"91403","county":"Los Angeles"},{"zip":"91404","county":"Los Angeles"},{"zip":"91405","county":"Los Angeles"},{"zip":"91406","county":"Los Angeles"},{"zip":"91407","county":"Los Angeles"},{"zip":"91408","county":"Los Angeles"},{"zip":"91409","county":"Los Angeles"},{"zip":"91410","county":"Los Angeles"},{"zip":"91411","county":"Los Angeles"},{"zip":"91412","county":"Los Angeles"},{"zip":"91413","county":"Los Angeles"},{"zip":"91416","county":"Los Angeles"},{"zip":"91423","county":"Los Angeles"},{"zip":"91426","county":"Los Angeles"},{"zip":"91436","county":"Los Angeles"},{"zip":"91470","county":"Los Angeles"},{"zip":"91482","county":"Los Angeles"},{"zip":"91495","county":"Los Angeles"},{"zip":"91496","county":"Los Angeles"},{"zip":"91497","county":"Los Angeles"},{"zip":"91499","county":"Los Angeles"},{"zip":"91501","county":"Los Angeles"},{"zip":"91502","county":"Los Angeles"},{"zip":"91503","county":"Los Angeles"},{"zip":"91504","county":"Los Angeles"},{"zip":"91505","county":"Los Angeles"},{"zip":"91506","county":"Los Angeles"},{"zip":"91507","county":"Los Angeles"},{"zip":"91508","county":"Los Angeles"},{"zip":"91510","county":"Los Angeles"},{"zip":"91521","county":"Los Angeles"},{"zip":"91522","county":"Los Angeles"},{"zip":"91523","county":"Los Angeles"},{"zip":"91526","county":"Los Angeles"},{"zip":"91601","county":"Los Angeles"},{"zip":"91602","county":"Los Angeles"},{"zip":"91603","county":"Los Angeles"},{"zip":"91604","county":"Los Angeles"},{"zip":"91605","county":"Los Angeles"},{"zip":"91606","county":"Los Angeles"},{"zip":"91607","county":"Los Angeles"},{"zip":"91608","county":"Los Angeles"},{"zip":"91609","county":"Los Angeles"},{"zip":"91610","county":"Los Angeles"},{"zip":"91611","county":"Los Angeles"},{"zip":"91612","county":"Los Angeles"},{"zip":"91614","county":"Los Angeles"},{"zip":"91615","county":"Los Angeles"},{"zip":"91616","county":"Los Angeles"},{"zip":"91617","county":"Los Angeles"},{"zip":"91618","county":"Los Angeles"},{"zip":"91701","county":"San Bernardino"},{"zip":"91702","county":"Los Angeles"},{"zip":"91706","county":"Los Angeles"},{"zip":"91708","county":"San Bernardino"},{"zip":"91709","county":"San Bernardino"},{"zip":"91710","county":"San Bernardino"},{"zip":"91711","county":"Los Angeles"},{"zip":"91714","county":"Los Angeles"},{"zip":"91715","county":"Los Angeles"},{"zip":"91716","county":"Los Angeles"},{"zip":"91722","county":"Los Angeles"},{"zip":"91723","county":"Los Angeles"},{"zip":"91724","county":"Los Angeles"},{"zip":"91729","county":"San Bernardino"},{"zip":"91730","county":"San Bernardino"},{"zip":"91731","county":"Los Angeles"},{"zip":"91732","county":"Los Angeles"},{"zip":"91733","county":"Los Angeles"},{"zip":"91734","county":"Los Angeles"},{"zip":"91735","county":"Los Angeles"},{"zip":"91737","county":"San Bernardino"},{"zip":"91739","county":"San Bernardino"},{"zip":"91740","county":"Los Angeles"},{"zip":"91741","county":"Los Angeles"},{"zip":"91743","county":"San Bernardino"},{"zip":"91744","county":"Los Angeles"},{"zip":"91745","county":"Los Angeles"},{"zip":"91746","county":"Los Angeles"},{"zip":"91747","county":"Los Angeles"},{"zip":"91748","county":"Los Angeles"},{"zip":"91749","county":"Los Angeles"},{"zip":"91750","county":"Los Angeles"},{"zip":"91752","county":"Riverside"},{"zip":"91754","county":"Los Angeles"},{"zip":"91755","county":"Los Angeles"},{"zip":"91756","county":"Los Angeles"},{"zip":"91758","county":"San Bernardino"},{"zip":"91759","county":"Los Angeles"},{"zip":"91761","county":"San Bernardino"},{"zip":"91762","county":"San Bernardino"},{"zip":"91763","county":"San Bernardino"},{"zip":"91764","county":"San Bernardino"},{"zip":"91765","county":"Los Angeles"},{"zip":"91766","county":"Los Angeles"},{"zip":"91767","county":"Los Angeles"},{"zip":"91768","county":"Los Angeles"},{"zip":"91769","county":"Los Angeles"},{"zip":"91770","county":"Los Angeles"},{"zip":"91771","county":"Los Angeles"},{"zip":"91772","county":"Los Angeles"},{"zip":"91773","county":"Los Angeles"},{"zip":"91775","county":"Los Angeles"},{"zip":"91776","county":"Los Angeles"},{"zip":"91778","county":"Los Angeles"},{"zip":"91780","county":"Los Angeles"},{"zip":"91784","county":"San Bernardino"},{"zip":"91785","county":"San Bernardino"},{"zip":"91786","county":"San Bernardino"},{"zip":"91788","county":"Los Angeles"},{"zip":"91789","county":"Los Angeles"},{"zip":"91790","county":"Los Angeles"},{"zip":"91791","county":"Los Angeles"},{"zip":"91792","county":"Los Angeles"},{"zip":"91793","county":"Los Angeles"},{"zip":"91795","county":"Los Angeles"},{"zip":"91797","county":"Los Angeles"},{"zip":"91798","county":"San Bernardino"},{"zip":"91799","county":"Los Angeles"},{"zip":"91801","county":"Los Angeles"},{"zip":"91802","county":"Los Angeles"},{"zip":"91803","county":"Los Angeles"},{"zip":"91804","county":"Los Angeles"},{"zip":"91841","county":"Los Angeles"},{"zip":"91896","county":"Los Angeles"},{"zip":"91899","county":"Los Angeles"},{"zip":"91901","county":"San Diego"},{"zip":"91902","county":"San Diego"},{"zip":"91903","county":"San Diego"},{"zip":"91905","county":"San Diego"},{"zip":"91906","county":"San Diego"},{"zip":"91908","county":"San Diego"},{"zip":"91909","county":"San Diego"},{"zip":"91910","county":"San Diego"},{"zip":"91911","county":"San Diego"},{"zip":"91912","county":"San Diego"},{"zip":"91913","county":"San Diego"},{"zip":"91914","county":"San Diego"},{"zip":"91915","county":"San Diego"},{"zip":"91916","county":"San Diego"},{"zip":"91917","county":"San Diego"},{"zip":"91921","county":"San Diego"},{"zip":"91931","county":"San Diego"},{"zip":"91932","county":"San Diego"},{"zip":"91933","county":"San Diego"},{"zip":"91934","county":"San Diego"},{"zip":"91935","county":"San Diego"},{"zip":"91941","county":"San Diego"},{"zip":"91942","county":"San Diego"},{"zip":"91943","county":"San Diego"},{"zip":"91944","county":"San Diego"},{"zip":"91945","county":"San Diego"},{"zip":"91946","county":"San Diego"},{"zip":"91947","county":"San Diego"},{"zip":"91948","county":"San Diego"},{"zip":"91950","county":"San Diego"},{"zip":"91951","county":"San Diego"},{"zip":"91962","county":"San Diego"},{"zip":"91963","county":"San Diego"},{"zip":"91976","county":"San Diego"},{"zip":"91977","county":"San Diego"},{"zip":"91978","county":"San Diego"},{"zip":"91979","county":"San Diego"},{"zip":"91980","county":"San Diego"},{"zip":"91987","county":"San Diego"},{"zip":"91990","county":"San Diego"},{"zip":"92003","county":"San Diego"},{"zip":"92004","county":"San Diego"},{"zip":"92007","county":"San Diego"},{"zip":"92008","county":"San Diego"},{"zip":"92009","county":"San Diego"},{"zip":"92010","county":"San Diego"},{"zip":"92011","county":"San Diego"},{"zip":"92013","county":"San Diego"},{"zip":"92014","county":"San Diego"},{"zip":"92018","county":"San Diego"},{"zip":"92019","county":"San Diego"},{"zip":"92020","county":"San Diego"},{"zip":"92021","county":"San Diego"},{"zip":"92022","county":"San Diego"},{"zip":"92023","county":"San Diego"},{"zip":"92024","county":"San Diego"},{"zip":"92025","county":"San Diego"},{"zip":"92026","county":"San Diego"},{"zip":"92027","county":"San Diego"},{"zip":"92028","county":"San Diego"},{"zip":"92029","county":"San Diego"},{"zip":"92030","county":"San Diego"},{"zip":"92033","county":"San Diego"},{"zip":"92036","county":"San Diego"},{"zip":"92037","county":"San Diego"},{"zip":"92038","county":"San Diego"},{"zip":"92039","county":"San Diego"},{"zip":"92040","county":"San Diego"},{"zip":"92046","county":"San Diego"},{"zip":"92049","county":"San Diego"},{"zip":"92051","county":"San Diego"},{"zip":"92052","county":"San Diego"},{"zip":"92054","county":"San Diego"},{"zip":"92055","county":"San Diego"},{"zip":"92056","county":"San Diego"},{"zip":"92057","county":"San Diego"},{"zip":"92059","county":"San Diego"},{"zip":"92060","county":"San Diego"},{"zip":"92061","county":"San Diego"},{"zip":"92064","county":"San Diego"},{"zip":"92065","county":"San Diego"},{"zip":"92066","county":"San Diego"},{"zip":"92067","county":"San Diego"},{"zip":"92068","county":"San Diego"},{"zip":"92069","county":"San Diego"},{"zip":"92070","county":"San Diego"},{"zip":"92071","county":"San Diego"},{"zip":"92072","county":"San Diego"},{"zip":"92074","county":"San Diego"},{"zip":"92075","county":"San Diego"},{"zip":"92078","county":"San Diego"},{"zip":"92079","county":"San Diego"},{"zip":"92081","county":"San Diego"},{"zip":"92082","county":"San Diego"},{"zip":"92083","county":"San Diego"},{"zip":"92084","county":"San Diego"},{"zip":"92085","county":"San Diego"},{"zip":"92086","county":"San Diego"},{"zip":"92088","county":"San Diego"},{"zip":"92090","county":"San Diego"},{"zip":"92091","county":"San Diego"},{"zip":"92092","county":"San Diego"},{"zip":"92093","county":"San Diego"},{"zip":"92096","county":"San Diego"},{"zip":"92101","county":"San Diego"},{"zip":"92102","county":"San Diego"},{"zip":"92103","county":"San Diego"},{"zip":"92104","county":"San Diego"},{"zip":"92105","county":"San Diego"},{"zip":"92106","county":"San Diego"},{"zip":"92107","county":"San Diego"},{"zip":"92108","county":"San Diego"},{"zip":"92109","county":"San Diego"},{"zip":"92110","county":"San Diego"},{"zip":"92111","county":"San Diego"},{"zip":"92112","county":"San Diego"},{"zip":"92113","county":"San Diego"},{"zip":"92114","county":"San Diego"},{"zip":"92115","county":"San Diego"},{"zip":"92116","county":"San Diego"},{"zip":"92117","county":"San Diego"},{"zip":"92118","county":"San Diego"},{"zip":"92119","county":"San Diego"},{"zip":"92120","county":"San Diego"},{"zip":"92121","county":"San Diego"},{"zip":"92122","county":"San Diego"},{"zip":"92123","county":"San Diego"},{"zip":"92124","county":"San Diego"},{"zip":"92126","county":"San Diego"},{"zip":"92127","county":"San Diego"},{"zip":"92128","county":"San Diego"},{"zip":"92129","county":"San Diego"},{"zip":"92130","county":"San Diego"},{"zip":"92131","county":"San Diego"},{"zip":"92132","county":"San Diego"},{"zip":"92133","county":"San Diego"},{"zip":"92134","county":"San Diego"},{"zip":"92135","county":"San Diego"},{"zip":"92136","county":"San Diego"},{"zip":"92137","county":"San Diego"},{"zip":"92138","county":"San Diego"},{"zip":"92139","county":"San Diego"},{"zip":"92140","county":"San Diego"},{"zip":"92142","county":"San Diego"},{"zip":"92143","county":"San Diego"},{"zip":"92145","county":"San Diego"},{"zip":"92147","county":"San Diego"},{"zip":"92149","county":"San Diego"},{"zip":"92150","county":"San Diego"},{"zip":"92152","county":"San Diego"},{"zip":"92153","county":"San Diego"},{"zip":"92154","county":"San Diego"},{"zip":"92155","county":"San Diego"},{"zip":"92158","county":"San Diego"},{"zip":"92159","county":"San Diego"},{"zip":"92160","county":"San Diego"},{"zip":"92161","county":"San Diego"},{"zip":"92162","county":"San Diego"},{"zip":"92163","county":"San Diego"},{"zip":"92164","county":"San Diego"},{"zip":"92165","county":"San Diego"},{"zip":"92166","county":"San Diego"},{"zip":"92167","county":"San Diego"},{"zip":"92168","county":"San Diego"},{"zip":"92169","county":"San Diego"},{"zip":"92170","county":"San Diego"},{"zip":"92171","county":"San Diego"},{"zip":"92172","county":"San Diego"},{"zip":"92173","county":"San Diego"},{"zip":"92174","county":"San Diego"},{"zip":"92175","county":"San Diego"},{"zip":"92176","county":"San Diego"},{"zip":"92177","county":"San Diego"},{"zip":"92178","county":"San Diego"},{"zip":"92179","county":"San Diego"},{"zip":"92182","county":"San Diego"},{"zip":"92184","county":"San Diego"},{"zip":"92186","county":"San Diego"},{"zip":"92187","county":"San Diego"},{"zip":"92190","county":"San Diego"},{"zip":"92191","county":"San Diego"},{"zip":"92192","county":"San Diego"},{"zip":"92193","county":"San Diego"},{"zip":"92194","county":"San Diego"},{"zip":"92195","county":"San Diego"},{"zip":"92196","county":"San Diego"},{"zip":"92197","county":"San Diego"},{"zip":"92198","county":"San Diego"},{"zip":"92199","county":"San Diego"},{"zip":"92201","county":"Riverside"},{"zip":"92202","county":"Riverside"},{"zip":"92203","county":"Riverside"},{"zip":"92210","county":"Riverside"},{"zip":"92211","county":"Riverside"},{"zip":"92220","county":"Riverside"},{"zip":"92222","county":"Imperial"},{"zip":"92223","county":"Riverside"},{"zip":"92225","county":"Riverside"},{"zip":"92226","county":"Riverside"},{"zip":"92227","county":"Imperial"},{"zip":"92230","county":"Riverside"},{"zip":"92231","county":"Imperial"},{"zip":"92232","county":"Imperial"},{"zip":"92233","county":"Imperial"},{"zip":"92234","county":"Riverside"},{"zip":"92235","county":"Riverside"},{"zip":"92236","county":"Riverside"},{"zip":"92239","county":"Riverside"},{"zip":"92240","county":"Riverside"},{"zip":"92241","county":"Riverside"},{"zip":"92242","county":"San Bernardino"},{"zip":"92243","county":"Imperial"},{"zip":"92244","county":"Imperial"},{"zip":"92247","county":"Riverside"},{"zip":"92248","county":"Riverside"},{"zip":"92249","county":"Imperial"},{"zip":"92250","county":"Imperial"},{"zip":"92251","county":"Imperial"},{"zip":"92252","county":"San Bernardino"},{"zip":"92253","county":"Riverside"},{"zip":"92254","county":"Riverside"},{"zip":"92255","county":"Riverside"},{"zip":"92256","county":"San Bernardino"},{"zip":"92257","county":"Imperial"},{"zip":"92258","county":"Riverside"},{"zip":"92259","county":"Imperial"},{"zip":"92260","county":"Riverside"},{"zip":"92261","county":"Riverside"},{"zip":"92262","county":"Riverside"},{"zip":"92263","county":"Riverside"},{"zip":"92264","county":"Riverside"},{"zip":"92266","county":"Imperial"},{"zip":"92267","county":"San Bernardino"},{"zip":"92268","county":"San Bernardino"},{"zip":"92270","county":"Riverside"},{"zip":"92273","county":"Imperial"},{"zip":"92274","county":"Riverside"},{"zip":"92275","county":"Imperial"},{"zip":"92276","county":"Riverside"},{"zip":"92277","county":"San Bernardino"},{"zip":"92278","county":"San Bernardino"},{"zip":"92280","county":"San Bernardino"},{"zip":"92281","county":"Imperial"},{"zip":"92282","county":"Riverside"},{"zip":"92283","county":"Imperial"},{"zip":"92284","county":"San Bernardino"},{"zip":"92285","county":"San Bernardino"},{"zip":"92286","county":"San Bernardino"},{"zip":"92292","county":"Riverside"},{"zip":"92301","county":"San Bernardino"},{"zip":"92304","county":"San Bernardino"},{"zip":"92305","county":"San Bernardino"},{"zip":"92307","county":"San Bernardino"},{"zip":"92308","county":"San Bernardino"},{"zip":"92309","county":"San Bernardino"},{"zip":"92310","county":"San Bernardino"},{"zip":"92311","county":"San Bernardino"},{"zip":"92312","county":"San Bernardino"},{"zip":"92313","county":"San Bernardino"},{"zip":"92314","county":"San Bernardino"},{"zip":"92315","county":"San Bernardino"},{"zip":"92316","county":"San Bernardino"},{"zip":"92317","county":"San Bernardino"},{"zip":"92318","county":"San Bernardino"},{"zip":"92320","county":"Riverside"},{"zip":"92321","county":"San Bernardino"},{"zip":"92322","county":"San Bernardino"},{"zip":"92323","county":"San Bernardino"},{"zip":"92324","county":"San Bernardino"},{"zip":"92325","county":"San Bernardino"},{"zip":"92326","county":"San Bernardino"},{"zip":"92327","county":"San Bernardino"},{"zip":"92328","county":"Inyo"},{"zip":"92329","county":"San Bernardino"},{"zip":"92331","county":"San Bernardino"},{"zip":"92332","county":"San Bernardino"},{"zip":"92333","county":"San Bernardino"},{"zip":"92334","county":"San Bernardino"},{"zip":"92335","county":"San Bernardino"},{"zip":"92336","county":"San Bernardino"},{"zip":"92337","county":"San Bernardino"},{"zip":"92338","county":"San Bernardino"},{"zip":"92339","county":"San Bernardino"},{"zip":"92340","county":"San Bernardino"},{"zip":"92341","county":"San Bernardino"},{"zip":"92342","county":"San Bernardino"},{"zip":"92344","county":"San Bernardino"},{"zip":"92345","county":"San Bernardino"},{"zip":"92346","county":"San Bernardino"},{"zip":"92347","county":"San Bernardino"},{"zip":"92350","county":"San Bernardino"},{"zip":"92352","county":"San Bernardino"},{"zip":"92354","county":"San Bernardino"},{"zip":"92356","county":"San Bernardino"},{"zip":"92357","county":"San Bernardino"},{"zip":"92358","county":"San Bernardino"},{"zip":"92359","county":"San Bernardino"},{"zip":"92363","county":"San Bernardino"},{"zip":"92364","county":"San Bernardino"},{"zip":"92365","county":"San Bernardino"},{"zip":"92366","county":"San Bernardino"},{"zip":"92368","county":"San Bernardino"},{"zip":"92369","county":"San Bernardino"},{"zip":"92371","county":"San Bernardino"},{"zip":"92372","county":"San Bernardino"},{"zip":"92373","county":"San Bernardino"},{"zip":"92374","county":"San Bernardino"},{"zip":"92375","county":"San Bernardino"},{"zip":"92376","county":"San Bernardino"},{"zip":"92377","county":"San Bernardino"},{"zip":"92378","county":"San Bernardino"},{"zip":"92382","county":"San Bernardino"},{"zip":"92384","county":"Inyo"},{"zip":"92385","county":"San Bernardino"},{"zip":"92386","county":"San Bernardino"},{"zip":"92389","county":"Inyo"},{"zip":"92391","county":"San Bernardino"},{"zip":"92392","county":"San Bernardino"},{"zip":"92393","county":"San Bernardino"},{"zip":"92394","county":"San Bernardino"},{"zip":"92395","county":"San Bernardino"},{"zip":"92397","county":"San Bernardino"},{"zip":"92398","county":"San Bernardino"},{"zip":"92399","county":"San Bernardino"},{"zip":"92401","county":"San Bernardino"},{"zip":"92402","county":"San Bernardino"},{"zip":"92403","county":"San Bernardino"},{"zip":"92404","county":"San Bernardino"},{"zip":"92405","county":"San Bernardino"},{"zip":"92406","county":"San Bernardino"},{"zip":"92407","county":"San Bernardino"},{"zip":"92408","county":"San Bernardino"},{"zip":"92410","county":"San Bernardino"},{"zip":"92411","county":"San Bernardino"},{"zip":"92412","county":"San Bernardino"},{"zip":"92413","county":"San Bernardino"},{"zip":"92414","county":"San Bernardino"},{"zip":"92415","county":"San Bernardino"},{"zip":"92418","county":"San Bernardino"},{"zip":"92423","county":"San Bernardino"},{"zip":"92424","county":"San Bernardino"},{"zip":"92427","county":"San Bernardino"},{"zip":"92501","county":"Riverside"},{"zip":"92502","county":"Riverside"},{"zip":"92503","county":"Riverside"},{"zip":"92504","county":"Riverside"},{"zip":"92505","county":"Riverside"},{"zip":"92506","county":"Riverside"},{"zip":"92507","county":"Riverside"},{"zip":"92508","county":"Riverside"},{"zip":"92509","county":"Riverside"},{"zip":"92513","county":"Riverside"},{"zip":"92514","county":"Riverside"},{"zip":"92515","county":"Riverside"},{"zip":"92516","county":"Riverside"},{"zip":"92517","county":"Riverside"},{"zip":"92518","county":"Riverside"},{"zip":"92519","county":"Riverside"},{"zip":"92521","county":"Riverside"},{"zip":"92522","county":"Riverside"},{"zip":"92530","county":"Riverside"},{"zip":"92531","county":"Riverside"},{"zip":"92532","county":"Riverside"},{"zip":"92536","county":"Riverside"},{"zip":"92539","county":"Riverside"},{"zip":"92543","county":"Riverside"},{"zip":"92544","county":"Riverside"},{"zip":"92545","county":"Riverside"},{"zip":"92546","county":"Riverside"},{"zip":"92548","county":"Riverside"},{"zip":"92549","county":"Riverside"},{"zip":"92551","county":"Riverside"},{"zip":"92552","county":"Riverside"},{"zip":"92553","county":"Riverside"},{"zip":"92554","county":"Riverside"},{"zip":"92555","county":"Riverside"},{"zip":"92556","county":"Riverside"},{"zip":"92557","county":"Riverside"},{"zip":"92561","county":"Riverside"},{"zip":"92562","county":"Riverside"},{"zip":"92563","county":"Riverside"},{"zip":"92564","county":"Riverside"},{"zip":"92567","county":"Riverside"},{"zip":"92570","county":"Riverside"},{"zip":"92571","county":"Riverside"},{"zip":"92572","county":"Riverside"},{"zip":"92581","county":"Riverside"},{"zip":"92582","county":"Riverside"},{"zip":"92583","county":"Riverside"},{"zip":"92584","county":"Riverside"},{"zip":"92585","county":"Riverside"},{"zip":"92586","county":"Riverside"},{"zip":"92587","county":"Riverside"},{"zip":"92589","county":"Riverside"},{"zip":"92590","county":"Riverside"},{"zip":"92591","county":"Riverside"},{"zip":"92592","county":"Riverside"},{"zip":"92593","county":"Riverside"},{"zip":"92595","county":"Riverside"},{"zip":"92596","county":"Riverside"},{"zip":"92599","county":"Riverside"},{"zip":"92602","county":"Orange"},{"zip":"92603","county":"Orange"},{"zip":"92604","county":"Orange"},{"zip":"92605","county":"Orange"},{"zip":"92606","county":"Orange"},{"zip":"92607","county":"Orange"},{"zip":"92609","county":"Orange"},{"zip":"92610","county":"Orange"},{"zip":"92612","county":"Orange"},{"zip":"92614","county":"Orange"},{"zip":"92615","county":"Orange"},{"zip":"92616","county":"Orange"},{"zip":"92617","county":"Orange"},{"zip":"92618","county":"Orange"},{"zip":"92619","county":"Orange"},{"zip":"92620","county":"Orange"},{"zip":"92623","county":"Orange"},{"zip":"92624","county":"Orange"},{"zip":"92625","county":"Orange"},{"zip":"92626","county":"Orange"},{"zip":"92627","county":"Orange"},{"zip":"92628","county":"Orange"},{"zip":"92629","county":"Orange"},{"zip":"92630","county":"Orange"},{"zip":"92637","county":"Orange"},{"zip":"92646","county":"Orange"},{"zip":"92647","county":"Orange"},{"zip":"92648","county":"Orange"},{"zip":"92649","county":"Orange"},{"zip":"92650","county":"Orange"},{"zip":"92651","county":"Orange"},{"zip":"92652","county":"Orange"},{"zip":"92653","county":"Orange"},{"zip":"92654","county":"Orange"},{"zip":"92655","county":"Orange"},{"zip":"92656","county":"Orange"},{"zip":"92657","county":"Orange"},{"zip":"92658","county":"Orange"},{"zip":"92659","county":"Orange"},{"zip":"92660","county":"Orange"},{"zip":"92661","county":"Orange"},{"zip":"92662","county":"Orange"},{"zip":"92663","county":"Orange"},{"zip":"92672","county":"Orange"},{"zip":"92673","county":"Orange"},{"zip":"92674","county":"Orange"},{"zip":"92675","county":"Orange"},{"zip":"92676","county":"Orange"},{"zip":"92677","county":"Orange"},{"zip":"92678","county":"Orange"},{"zip":"92679","county":"Orange"},{"zip":"92683","county":"Orange"},{"zip":"92684","county":"Orange"},{"zip":"92685","county":"Orange"},{"zip":"92688","county":"Orange"},{"zip":"92690","county":"Orange"},{"zip":"92691","county":"Orange"},{"zip":"92692","county":"Orange"},{"zip":"92693","county":"Orange"},{"zip":"92694","county":"Orange"},{"zip":"92697","county":"Orange"},{"zip":"92698","county":"Orange"},{"zip":"92701","county":"Orange"},{"zip":"92702","county":"Orange"},{"zip":"92703","county":"Orange"},{"zip":"92704","county":"Orange"},{"zip":"92705","county":"Orange"},{"zip":"92706","county":"Orange"},{"zip":"92707","county":"Orange"},{"zip":"92708","county":"Orange"},{"zip":"92709","county":"Orange"},{"zip":"92710","county":"Orange"},{"zip":"92711","county":"Orange"},{"zip":"92712","county":"Orange"},{"zip":"92725","county":"Orange"},{"zip":"92728","county":"Orange"},{"zip":"92735","county":"Orange"},{"zip":"92780","county":"Orange"},{"zip":"92781","county":"Orange"},{"zip":"92782","county":"Orange"},{"zip":"92799","county":"Orange"},{"zip":"92801","county":"Orange"},{"zip":"92802","county":"Orange"},{"zip":"92803","county":"Orange"},{"zip":"92804","county":"Orange"},{"zip":"92805","county":"Orange"},{"zip":"92806","county":"Orange"},{"zip":"92807","county":"Orange"},{"zip":"92808","county":"Orange"},{"zip":"92809","county":"Orange"},{"zip":"92811","county":"Orange"},{"zip":"92812","county":"Orange"},{"zip":"92814","county":"Orange"},{"zip":"92815","county":"Orange"},{"zip":"92816","county":"Orange"},{"zip":"92817","county":"Orange"},{"zip":"92821","county":"Orange"},{"zip":"92822","county":"Orange"},{"zip":"92823","county":"Orange"},{"zip":"92825","county":"Orange"},{"zip":"92831","county":"Orange"},{"zip":"92832","county":"Orange"},{"zip":"92833","county":"Orange"},{"zip":"92834","county":"Orange"},{"zip":"92835","county":"Orange"},{"zip":"92836","county":"Orange"},{"zip":"92837","county":"Orange"},{"zip":"92838","county":"Orange"},{"zip":"92840","county":"Orange"},{"zip":"92841","county":"Orange"},{"zip":"92842","county":"Orange"},{"zip":"92843","county":"Orange"},{"zip":"92844","county":"Orange"},{"zip":"92845","county":"Orange"},{"zip":"92846","county":"Orange"},{"zip":"92850","county":"Orange"},{"zip":"92856","county":"Orange"},{"zip":"92857","county":"Orange"},{"zip":"92859","county":"Orange"},{"zip":"92860","county":"Riverside"},{"zip":"92861","county":"Orange"},{"zip":"92862","county":"Orange"},{"zip":"92863","county":"Orange"},{"zip":"92864","county":"Orange"},{"zip":"92865","county":"Orange"},{"zip":"92866","county":"Orange"},{"zip":"92867","county":"Orange"},{"zip":"92868","county":"Orange"},{"zip":"92869","county":"Orange"},{"zip":"92870","county":"Orange"},{"zip":"92871","county":"Orange"},{"zip":"92877","county":"Riverside"},{"zip":"92878","county":"Riverside"},{"zip":"92879","county":"Riverside"},{"zip":"92880","county":"Riverside"},{"zip":"92881","county":"Riverside"},{"zip":"92882","county":"Riverside"},{"zip":"92883","county":"Riverside"},{"zip":"92885","county":"Orange"},{"zip":"92886","county":"Orange"},{"zip":"92887","county":"Orange"},{"zip":"92899","county":"Orange"},{"zip":"93001","county":"Ventura"},{"zip":"93002","county":"Ventura"},{"zip":"93003","county":"Ventura"},{"zip":"93004","county":"Ventura"},{"zip":"93005","county":"Ventura"},{"zip":"93006","county":"Ventura"},{"zip":"93007","county":"Ventura"},{"zip":"93009","county":"Ventura"},{"zip":"93010","county":"Ventura"},{"zip":"93011","county":"Ventura"},{"zip":"93012","county":"Ventura"},{"zip":"93013","county":"Santa Barbara"},{"zip":"93014","county":"Santa Barbara"},{"zip":"93015","county":"Ventura"},{"zip":"93016","county":"Ventura"},{"zip":"93020","county":"Ventura"},{"zip":"93021","county":"Ventura"},{"zip":"93022","county":"Ventura"},{"zip":"93023","county":"Ventura"},{"zip":"93024","county":"Ventura"},{"zip":"93030","county":"Ventura"},{"zip":"93031","county":"Ventura"},{"zip":"93032","county":"Ventura"},{"zip":"93033","county":"Ventura"},{"zip":"93034","county":"Ventura"},{"zip":"93035","county":"Ventura"},{"zip":"93036","county":"Ventura"},{"zip":"93040","county":"Ventura"},{"zip":"93041","county":"Ventura"},{"zip":"93042","county":"Ventura"},{"zip":"93043","county":"Ventura"},{"zip":"93044","county":"Ventura"},{"zip":"93060","county":"Ventura"},{"zip":"93061","county":"Ventura"},{"zip":"93062","county":"Ventura"},{"zip":"93063","county":"Ventura"},{"zip":"93064","county":"Ventura"},{"zip":"93065","county":"Ventura"},{"zip":"93066","county":"Ventura"},{"zip":"93067","county":"Santa Barbara"},{"zip":"93093","county":"Ventura"},{"zip":"93094","county":"Ventura"},{"zip":"93099","county":"Ventura"},{"zip":"93101","county":"Santa Barbara"},{"zip":"93102","county":"Santa Barbara"},{"zip":"93103","county":"Santa Barbara"},{"zip":"93105","county":"Santa Barbara"},{"zip":"93106","county":"Santa Barbara"},{"zip":"93107","county":"Santa Barbara"},{"zip":"93108","county":"Santa Barbara"},{"zip":"93109","county":"Santa Barbara"},{"zip":"93110","county":"Santa Barbara"},{"zip":"93111","county":"Santa Barbara"},{"zip":"93116","county":"Santa Barbara"},{"zip":"93117","county":"Santa Barbara"},{"zip":"93118","county":"Santa Barbara"},{"zip":"93120","county":"Santa Barbara"},{"zip":"93121","county":"Santa Barbara"},{"zip":"93130","county":"Santa Barbara"},{"zip":"93140","county":"Santa Barbara"},{"zip":"93150","county":"Santa Barbara"},{"zip":"93160","county":"Santa Barbara"},{"zip":"93190","county":"Santa Barbara"},{"zip":"93199","county":"Santa Barbara"},{"zip":"93201","county":"Tulare"},{"zip":"93202","county":"Kings"},{"zip":"93203","county":"Kern"},{"zip":"93204","county":"Kings"},{"zip":"93205","county":"Kern"},{"zip":"93206","county":"Kern"},{"zip":"93207","county":"Tulare"},{"zip":"93208","county":"Tulare"},{"zip":"93210","county":"Fresno"},{"zip":"93212","county":"Kings"},{"zip":"93215","county":"Kern"},{"zip":"93216","county":"Kern"},{"zip":"93218","county":"Tulare"},{"zip":"93219","county":"Tulare"},{"zip":"93220","county":"Kern"},{"zip":"93221","county":"Tulare"},{"zip":"93222","county":"Kern"},{"zip":"93223","county":"Tulare"},{"zip":"93224","county":"Kern"},{"zip":"93225","county":"Kern"},{"zip":"93226","county":"Kern"},{"zip":"93227","county":"Tulare"},{"zip":"93230","county":"Kings"},{"zip":"93232","county":"Kings"},{"zip":"93234","county":"Fresno"},{"zip":"93235","county":"Tulare"},{"zip":"93237","county":"Tulare"},{"zip":"93238","county":"Kern"},{"zip":"93239","county":"Kings"},{"zip":"93240","county":"Kern"},{"zip":"93241","county":"Kern"},{"zip":"93242","county":"Fresno"},{"zip":"93243","county":"Kern"},{"zip":"93244","county":"Tulare"},{"zip":"93245","county":"Kings"},{"zip":"93246","county":"Kings"},{"zip":"93247","county":"Tulare"},{"zip":"93249","county":"Kern"},{"zip":"93250","county":"Kern"},{"zip":"93251","county":"Kern"},{"zip":"93252","county":"Kern"},{"zip":"93254","county":"Santa Barbara"},{"zip":"93255","county":"Kern"},{"zip":"93256","county":"Tulare"},{"zip":"93257","county":"Tulare"},{"zip":"93258","county":"Tulare"},{"zip":"93260","county":"Tulare"},{"zip":"93261","county":"Tulare"},{"zip":"93262","county":"Tulare"},{"zip":"93263","county":"Kern"},{"zip":"93265","county":"Tulare"},{"zip":"93266","county":"Kings"},{"zip":"93267","county":"Tulare"},{"zip":"93268","county":"Kern"},{"zip":"93270","county":"Tulare"},{"zip":"93271","county":"Tulare"},{"zip":"93272","county":"Tulare"},{"zip":"93274","county":"Tulare"},{"zip":"93275","county":"Tulare"},{"zip":"93276","county":"Kern"},{"zip":"93277","county":"Tulare"},{"zip":"93278","county":"Tulare"},{"zip":"93279","county":"Tulare"},{"zip":"93280","county":"Kern"},{"zip":"93282","county":"Tulare"},{"zip":"93283","county":"Kern"},{"zip":"93285","county":"Kern"},{"zip":"93286","county":"Tulare"},{"zip":"93287","county":"Kern"},{"zip":"93290","county":"Tulare"},{"zip":"93291","county":"Tulare"},{"zip":"93292","county":"Tulare"},{"zip":"93301","county":"Kern"},{"zip":"93302","county":"Kern"},{"zip":"93303","county":"Kern"},{"zip":"93304","county":"Kern"},{"zip":"93305","county":"Kern"},{"zip":"93306","county":"Kern"},{"zip":"93307","county":"Kern"},{"zip":"93308","county":"Kern"},{"zip":"93309","county":"Kern"},{"zip":"93311","county":"Kern"},{"zip":"93312","county":"Kern"},{"zip":"93313","county":"Kern"},{"zip":"93314","county":"Kern"},{"zip":"93380","county":"Kern"},{"zip":"93381","county":"Kern"},{"zip":"93382","county":"Kern"},{"zip":"93383","county":"Kern"},{"zip":"93384","county":"Kern"},{"zip":"93385","county":"Kern"},{"zip":"93386","county":"Kern"},{"zip":"93387","county":"Kern"},{"zip":"93388","county":"Kern"},{"zip":"93389","county":"Kern"},{"zip":"93390","county":"Kern"},{"zip":"93401","county":"San Luis Obispo"},{"zip":"93402","county":"San Luis Obispo"},{"zip":"93403","county":"San Luis Obispo"},{"zip":"93405","county":"San Luis Obispo"},{"zip":"93406","county":"San Luis Obispo"},{"zip":"93407","county":"San Luis Obispo"},{"zip":"93408","county":"San Luis Obispo"},{"zip":"93409","county":"San Luis Obispo"},{"zip":"93410","county":"San Luis Obispo"},{"zip":"93412","county":"San Luis Obispo"},{"zip":"93420","county":"San Luis Obispo"},{"zip":"93421","county":"San Luis Obispo"},{"zip":"93422","county":"San Luis Obispo"},{"zip":"93423","county":"San Luis Obispo"},{"zip":"93424","county":"San Luis Obispo"},{"zip":"93426","county":"Monterey"},{"zip":"93427","county":"Santa Barbara"},{"zip":"93428","county":"San Luis Obispo"},{"zip":"93429","county":"Santa Barbara"},{"zip":"93430","county":"San Luis Obispo"},{"zip":"93432","county":"San Luis Obispo"},{"zip":"93433","county":"San Luis Obispo"},{"zip":"93434","county":"Santa Barbara"},{"zip":"93435","county":"San Luis Obispo"},{"zip":"93436","county":"Santa Barbara"},{"zip":"93437","county":"Santa Barbara"},{"zip":"93438","county":"Santa Barbara"},{"zip":"93440","county":"Santa Barbara"},{"zip":"93441","county":"Santa Barbara"},{"zip":"93442","county":"San Luis Obispo"},{"zip":"93443","county":"San Luis Obispo"},{"zip":"93444","county":"San Luis Obispo"},{"zip":"93445","county":"San Luis Obispo"},{"zip":"93446","county":"San Luis Obispo"},{"zip":"93447","county":"San Luis Obispo"},{"zip":"93448","county":"San Luis Obispo"},{"zip":"93449","county":"San Luis Obispo"},{"zip":"93450","county":"Monterey"},{"zip":"93451","county":"San Luis Obispo"},{"zip":"93452","county":"San Luis Obispo"},{"zip":"93453","county":"San Luis Obispo"},{"zip":"93454","county":"Santa Barbara"},{"zip":"93455","county":"Santa Barbara"},{"zip":"93456","county":"Santa Barbara"},{"zip":"93457","county":"Santa Barbara"},{"zip":"93458","county":"Santa Barbara"},{"zip":"93460","county":"Santa Barbara"},{"zip":"93461","county":"San Luis Obispo"},{"zip":"93463","county":"Santa Barbara"},{"zip":"93464","county":"Santa Barbara"},{"zip":"93465","county":"San Luis Obispo"},{"zip":"93475","county":"San Luis Obispo"},{"zip":"93483","county":"San Luis Obispo"},{"zip":"93501","county":"Kern"},{"zip":"93502","county":"Kern"},{"zip":"93504","county":"Kern"},{"zip":"93505","county":"Kern"},{"zip":"93510","county":"Los Angeles"},{"zip":"93512","county":"Mono"},{"zip":"93513","county":"Inyo"},{"zip":"93514","county":"Inyo"},{"zip":"93515","county":"Inyo"},{"zip":"93516","county":"Kern"},{"zip":"93517","county":"Mono"},{"zip":"93518","county":"Kern"},{"zip":"93519","county":"Kern"},{"zip":"93522","county":"Inyo"},{"zip":"93523","county":"Kern"},{"zip":"93524","county":"Kern"},{"zip":"93526","county":"Inyo"},{"zip":"93527","county":"Kern"},{"zip":"93528","county":"Kern"},{"zip":"93529","county":"Mono"},{"zip":"93530","county":"Inyo"},{"zip":"93531","county":"Kern"},{"zip":"93532","county":"Los Angeles"},{"zip":"93534","county":"Los Angeles"},{"zip":"93535","county":"Los Angeles"},{"zip":"93536","county":"Los Angeles"},{"zip":"93539","county":"Los Angeles"},{"zip":"93541","county":"Mono"},{"zip":"93542","county":"Inyo"},{"zip":"93543","county":"Los Angeles"},{"zip":"93544","county":"Los Angeles"},{"zip":"93545","county":"Inyo"},{"zip":"93546","county":"Mono"},{"zip":"93549","county":"Inyo"},{"zip":"93550","county":"Los Angeles"},{"zip":"93551","county":"Los Angeles"},{"zip":"93552","county":"Los Angeles"},{"zip":"93553","county":"Los Angeles"},{"zip":"93554","county":"Kern"},{"zip":"93555","county":"Kern"},{"zip":"93556","county":"Kern"},{"zip":"93558","county":"San Bernardino"},{"zip":"93560","county":"Kern"},{"zip":"93561","county":"Kern"},{"zip":"93562","county":"San Bernardino"},{"zip":"93563","county":"Los Angeles"},{"zip":"93581","county":"Kern"},{"zip":"93584","county":"Los Angeles"},{"zip":"93586","county":"Los Angeles"},{"zip":"93590","county":"Los Angeles"},{"zip":"93591","county":"Los Angeles"},{"zip":"93592","county":"San Bernardino"},{"zip":"93596","county":"Kern"},{"zip":"93599","county":"Los Angeles"},{"zip":"93601","county":"Madera"},{"zip":"93602","county":"Fresno"},{"zip":"93603","county":"Tulare"},{"zip":"93604","county":"Madera"},{"zip":"93605","county":"Fresno"},{"zip":"93606","county":"Fresno"},{"zip":"93607","county":"Fresno"},{"zip":"93608","county":"Fresno"},{"zip":"93609","county":"Fresno"},{"zip":"93610","county":"Madera"},{"zip":"93611","county":"Fresno"},{"zip":"93612","county":"Fresno"},{"zip":"93613","county":"Fresno"},{"zip":"93614","county":"Madera"},{"zip":"93615","county":"Tulare"},{"zip":"93616","county":"Fresno"},{"zip":"93618","county":"Tulare"},{"zip":"93619","county":"Fresno"},{"zip":"93620","county":"Merced"},{"zip":"93621","county":"Fresno"},{"zip":"93622","county":"Fresno"},{"zip":"93623","county":"Mariposa"},{"zip":"93624","county":"Fresno"},{"zip":"93625","county":"Fresno"},{"zip":"93626","county":"Fresno"},{"zip":"93627","county":"Fresno"},{"zip":"93628","county":"Fresno"},{"zip":"93630","county":"Fresno"},{"zip":"93631","county":"Fresno"},{"zip":"93633","county":"Tulare"},{"zip":"93634","county":"Fresno"},{"zip":"93635","county":"Merced"},{"zip":"93636","county":"Madera"},{"zip":"93637","county":"Madera"},{"zip":"93638","county":"Madera"},{"zip":"93639","county":"Madera"},{"zip":"93640","county":"Fresno"},{"zip":"93641","county":"Fresno"},{"zip":"93642","county":"Fresno"},{"zip":"93643","county":"Madera"},{"zip":"93644","county":"Madera"},{"zip":"93645","county":"Madera"},{"zip":"93646","county":"Fresno"},{"zip":"93647","county":"Tulare"},{"zip":"93648","county":"Fresno"},{"zip":"93649","county":"Fresno"},{"zip":"93650","county":"Fresno"},{"zip":"93651","county":"Fresno"},{"zip":"93652","county":"Fresno"},{"zip":"93653","county":"Madera"},{"zip":"93654","county":"Fresno"},{"zip":"93656","county":"Fresno"},{"zip":"93657","county":"Fresno"},{"zip":"93660","county":"Fresno"},{"zip":"93661","county":"Merced"},{"zip":"93662","county":"Fresno"},{"zip":"93664","county":"Fresno"},{"zip":"93665","county":"Merced"},{"zip":"93666","county":"Tulare"},{"zip":"93667","county":"Fresno"},{"zip":"93668","county":"Fresno"},{"zip":"93669","county":"Madera"},{"zip":"93670","county":"Tulare"},{"zip":"93673","county":"Tulare"},{"zip":"93675","county":"Fresno"},{"zip":"93701","county":"Fresno"},{"zip":"93702","county":"Fresno"},{"zip":"93703","county":"Fresno"},{"zip":"93704","county":"Fresno"},{"zip":"93705","county":"Fresno"},{"zip":"93706","county":"Fresno"},{"zip":"93707","county":"Fresno"},{"zip":"93708","county":"Fresno"},{"zip":"93709","county":"Fresno"},{"zip":"93710","county":"Fresno"},{"zip":"93711","county":"Fresno"},{"zip":"93712","county":"Fresno"},{"zip":"93714","county":"Fresno"},{"zip":"93715","county":"Fresno"},{"zip":"93716","county":"Fresno"},{"zip":"93717","county":"Fresno"},{"zip":"93718","county":"Fresno"},{"zip":"93720","county":"Fresno"},{"zip":"93721","county":"Fresno"},{"zip":"93722","county":"Fresno"},{"zip":"93723","county":"Fresno"},{"zip":"93724","county":"Fresno"},{"zip":"93725","county":"Fresno"},{"zip":"93726","county":"Fresno"},{"zip":"93727","county":"Fresno"},{"zip":"93728","county":"Fresno"},{"zip":"93729","county":"Fresno"},{"zip":"93730","county":"Fresno"},{"zip":"93740","county":"Fresno"},{"zip":"93741","county":"Fresno"},{"zip":"93744","county":"Fresno"},{"zip":"93745","county":"Fresno"},{"zip":"93747","county":"Fresno"},{"zip":"93750","county":"Fresno"},{"zip":"93755","county":"Fresno"},{"zip":"93760","county":"Fresno"},{"zip":"93761","county":"Fresno"},{"zip":"93764","county":"Fresno"},{"zip":"93765","county":"Fresno"},{"zip":"93771","county":"Fresno"},{"zip":"93772","county":"Fresno"},{"zip":"93773","county":"Fresno"},{"zip":"93774","county":"Fresno"},{"zip":"93775","county":"Fresno"},{"zip":"93776","county":"Fresno"},{"zip":"93777","county":"Fresno"},{"zip":"93778","county":"Fresno"},{"zip":"93779","county":"Fresno"},{"zip":"93780","county":"Fresno"},{"zip":"93784","county":"Fresno"},{"zip":"93786","county":"Fresno"},{"zip":"93790","county":"Fresno"},{"zip":"93791","county":"Fresno"},{"zip":"93792","county":"Fresno"},{"zip":"93793","county":"Fresno"},{"zip":"93794","county":"Fresno"},{"zip":"93844","county":"Fresno"},{"zip":"93888","county":"Fresno"},{"zip":"93901","county":"Monterey"},{"zip":"93902","county":"Monterey"},{"zip":"93905","county":"Monterey"},{"zip":"93906","county":"Monterey"},{"zip":"93907","county":"Monterey"},{"zip":"93908","county":"Monterey"},{"zip":"93912","county":"Monterey"},{"zip":"93915","county":"Monterey"},{"zip":"93920","county":"Monterey"},{"zip":"93921","county":"Monterey"},{"zip":"93922","county":"Monterey"},{"zip":"93923","county":"Monterey"},{"zip":"93924","county":"Monterey"},{"zip":"93925","county":"Monterey"},{"zip":"93926","county":"Monterey"},{"zip":"93927","county":"Monterey"},{"zip":"93928","county":"Monterey"},{"zip":"93930","county":"Monterey"},{"zip":"93932","county":"Monterey"},{"zip":"93933","county":"Monterey"},{"zip":"93940","county":"Monterey"},{"zip":"93942","county":"Monterey"},{"zip":"93943","county":"Monterey"},{"zip":"93944","county":"Monterey"},{"zip":"93950","county":"Monterey"},{"zip":"93953","county":"Monterey"},{"zip":"93954","county":"Monterey"},{"zip":"93955","county":"Monterey"},{"zip":"93960","county":"Monterey"},{"zip":"93962","county":"Monterey"},{"zip":"94002","county":"San Mateo"},{"zip":"94005","county":"San Mateo"},{"zip":"94010","county":"San Mateo"},{"zip":"94011","county":"San Mateo"},{"zip":"94013","county":"San Mateo"},{"zip":"94014","county":"San Mateo"},{"zip":"94015","county":"San Mateo"},{"zip":"94016","county":"San Mateo"},{"zip":"94017","county":"San Mateo"},{"zip":"94018","county":"San Mateo"},{"zip":"94019","county":"San Mateo"},{"zip":"94020","county":"San Mateo"},{"zip":"94021","county":"San Mateo"},{"zip":"94022","county":"Santa Clara"},{"zip":"94023","county":"Santa Clara"},{"zip":"94024","county":"Santa Clara"},{"zip":"94025","county":"San Mateo"},{"zip":"94026","county":"San Mateo"},{"zip":"94027","county":"San Mateo"},{"zip":"94028","county":"San Mateo"},{"zip":"94030","county":"San Mateo"},{"zip":"94035","county":"Santa Clara"},{"zip":"94037","county":"San Mateo"},{"zip":"94038","county":"San Mateo"},{"zip":"94039","county":"Santa Clara"},{"zip":"94040","county":"Santa Clara"},{"zip":"94041","county":"Santa Clara"},{"zip":"94042","county":"Santa Clara"},{"zip":"94043","county":"Santa Clara"},{"zip":"94044","county":"San Mateo"},{"zip":"94060","county":"San Mateo"},{"zip":"94061","county":"San Mateo"},{"zip":"94062","county":"San Mateo"},{"zip":"94063","county":"San Mateo"},{"zip":"94064","county":"San Mateo"},{"zip":"94065","county":"San Mateo"},{"zip":"94066","county":"San Mateo"},{"zip":"94070","county":"San Mateo"},{"zip":"94074","county":"San Mateo"},{"zip":"94080","county":"San Mateo"},{"zip":"94083","county":"San Mateo"},{"zip":"94085","county":"Santa Clara"},{"zip":"94086","county":"Santa Clara"},{"zip":"94087","county":"Santa Clara"},{"zip":"94088","county":"Santa Clara"},{"zip":"94089","county":"Santa Clara"},{"zip":"94096","county":"San Mateo"},{"zip":"94098","county":"San Mateo"},{"zip":"94101","county":"San Francisco"},{"zip":"94102","county":"San Francisco"},{"zip":"94103","county":"San Francisco"},{"zip":"94104","county":"San Francisco"},{"zip":"94105","county":"San Francisco"},{"zip":"94106","county":"San Francisco"},{"zip":"94107","county":"San Francisco"},{"zip":"94108","county":"San Francisco"},{"zip":"94109","county":"San Francisco"},{"zip":"94110","county":"San Francisco"},{"zip":"94111","county":"San Francisco"},{"zip":"94112","county":"San Francisco"},{"zip":"94114","county":"San Francisco"},{"zip":"94115","county":"San Francisco"},{"zip":"94116","county":"San Francisco"},{"zip":"94117","county":"San Francisco"},{"zip":"94118","county":"San Francisco"},{"zip":"94119","county":"San Francisco"},{"zip":"94120","county":"San Francisco"},{"zip":"94121","county":"San Francisco"},{"zip":"94122","county":"San Francisco"},{"zip":"94123","county":"San Francisco"},{"zip":"94124","county":"San Francisco"},{"zip":"94125","county":"San Francisco"},{"zip":"94126","county":"San Francisco"},{"zip":"94127","county":"San Francisco"},{"zip":"94128","county":"San Mateo"},{"zip":"94129","county":"San Francisco"},{"zip":"94130","county":"San Francisco"},{"zip":"94131","county":"San Francisco"},{"zip":"94132","county":"San Francisco"},{"zip":"94133","county":"San Francisco"},{"zip":"94134","county":"San Francisco"},{"zip":"94135","county":"San Francisco"},{"zip":"94136","county":"San Francisco"},{"zip":"94137","county":"San Francisco"},{"zip":"94138","county":"San Francisco"},{"zip":"94139","county":"San Francisco"},{"zip":"94140","county":"San Francisco"},{"zip":"94141","county":"San Francisco"},{"zip":"94142","county":"San Francisco"},{"zip":"94143","county":"San Francisco"},{"zip":"94144","county":"San Francisco"},{"zip":"94145","county":"San Francisco"},{"zip":"94146","county":"San Francisco"},{"zip":"94147","county":"San Francisco"},{"zip":"94150","county":"San Francisco"},{"zip":"94151","county":"San Francisco"},{"zip":"94152","county":"San Francisco"},{"zip":"94153","county":"San Francisco"},{"zip":"94154","county":"San Francisco"},{"zip":"94155","county":"San Francisco"},{"zip":"94156","county":"San Francisco"},{"zip":"94157","county":"San Francisco"},{"zip":"94158","county":"San Francisco"},{"zip":"94159","county":"San Francisco"},{"zip":"94160","county":"San Francisco"},{"zip":"94161","county":"San Francisco"},{"zip":"94162","county":"San Francisco"},{"zip":"94163","county":"San Francisco"},{"zip":"94164","county":"San Francisco"},{"zip":"94165","county":"San Francisco"},{"zip":"94166","county":"San Francisco"},{"zip":"94167","county":"San Francisco"},{"zip":"94168","county":"San Francisco"},{"zip":"94169","county":"San Francisco"},{"zip":"94170","county":"San Francisco"},{"zip":"94171","county":"San Francisco"},{"zip":"94172","county":"San Francisco"},{"zip":"94175","county":"San Francisco"},{"zip":"94177","county":"San Francisco"},{"zip":"94188","county":"San Francisco"},{"zip":"94199","county":"San Francisco"},{"zip":"94203","county":"Sacramento"},{"zip":"94204","county":"Sacramento"},{"zip":"94205","county":"Sacramento"},{"zip":"94206","county":"Sacramento"},{"zip":"94207","county":"Sacramento"},{"zip":"94208","county":"Sacramento"},{"zip":"94209","county":"Sacramento"},{"zip":"94211","county":"Sacramento"},{"zip":"94229","county":"Sacramento"},{"zip":"94230","county":"Sacramento"},{"zip":"94232","county":"Sacramento"},{"zip":"94234","county":"Sacramento"},{"zip":"94235","county":"Sacramento"},{"zip":"94236","county":"Sacramento"},{"zip":"94237","county":"Sacramento"},{"zip":"94239","county":"Sacramento"},{"zip":"94240","county":"Sacramento"},{"zip":"94244","county":"Sacramento"},{"zip":"94245","county":"Sacramento"},{"zip":"94246","county":"Sacramento"},{"zip":"94247","county":"Sacramento"},{"zip":"94248","county":"Sacramento"},{"zip":"94249","county":"Sacramento"},{"zip":"94250","county":"Sacramento"},{"zip":"94252","county":"Sacramento"},{"zip":"94254","county":"Sacramento"},{"zip":"94256","county":"Sacramento"},{"zip":"94257","county":"Sacramento"},{"zip":"94258","county":"Sacramento"},{"zip":"94259","county":"Sacramento"},{"zip":"94261","county":"Sacramento"},{"zip":"94262","county":"Sacramento"},{"zip":"94263","county":"Sacramento"},{"zip":"94267","county":"Sacramento"},{"zip":"94268","county":"Sacramento"},{"zip":"94269","county":"Sacramento"},{"zip":"94271","county":"Sacramento"},{"zip":"94273","county":"Sacramento"},{"zip":"94274","county":"Sacramento"},{"zip":"94277","county":"Sacramento"},{"zip":"94278","county":"Sacramento"},{"zip":"94279","county":"Sacramento"},{"zip":"94280","county":"Sacramento"},{"zip":"94282","county":"Sacramento"},{"zip":"94283","county":"Sacramento"},{"zip":"94284","county":"Sacramento"},{"zip":"94285","county":"Sacramento"},{"zip":"94286","county":"Sacramento"},{"zip":"94287","county":"Sacramento"},{"zip":"94288","county":"Sacramento"},{"zip":"94289","county":"Sacramento"},{"zip":"94290","county":"Sacramento"},{"zip":"94291","county":"Sacramento"},{"zip":"94293","county":"Sacramento"},{"zip":"94294","county":"Sacramento"},{"zip":"94295","county":"Sacramento"},{"zip":"94296","county":"Sacramento"},{"zip":"94297","county":"Sacramento"},{"zip":"94298","county":"Sacramento"},{"zip":"94299","county":"Sacramento"},{"zip":"94301","county":"Santa Clara"},{"zip":"94302","county":"Santa Clara"},{"zip":"94303","county":"Santa Clara"},{"zip":"94304","county":"Santa Clara"},{"zip":"94305","county":"Santa Clara"},{"zip":"94306","county":"Santa Clara"},{"zip":"94309","county":"Santa Clara"},{"zip":"94401","county":"San Mateo"},{"zip":"94402","county":"San Mateo"},{"zip":"94403","county":"San Mateo"},{"zip":"94404","county":"San Mateo"},{"zip":"94497","county":"San Mateo"},{"zip":"94501","county":"Alameda"},{"zip":"94502","county":"Alameda"},{"zip":"94503","county":"Napa"},{"zip":"94506","county":"Contra Costa"},{"zip":"94507","county":"Contra Costa"},{"zip":"94508","county":"Napa"},{"zip":"94509","county":"Contra Costa"},{"zip":"94510","county":"Solano"},{"zip":"94511","county":"Contra Costa"},{"zip":"94512","county":"Solano"},{"zip":"94513","county":"Contra Costa"},{"zip":"94514","county":"Contra Costa"},{"zip":"94515","county":"Napa"},{"zip":"94516","county":"Contra Costa"},{"zip":"94517","county":"Contra Costa"},{"zip":"94518","county":"Contra Costa"},{"zip":"94519","county":"Contra Costa"},{"zip":"94520","county":"Contra Costa"},{"zip":"94521","county":"Contra Costa"},{"zip":"94522","county":"Contra Costa"},{"zip":"94523","county":"Contra Costa"},{"zip":"94524","county":"Contra Costa"},{"zip":"94525","county":"Contra Costa"},{"zip":"94526","county":"Contra Costa"},{"zip":"94527","county":"Contra Costa"},{"zip":"94528","county":"Contra Costa"},{"zip":"94529","county":"Contra Costa"},{"zip":"94530","county":"Contra Costa"},{"zip":"94531","county":"Contra Costa"},{"zip":"94533","county":"Solano"},{"zip":"94534","county":"Solano"},{"zip":"94535","county":"Solano"},{"zip":"94536","county":"Alameda"},{"zip":"94537","county":"Alameda"},{"zip":"94538","county":"Alameda"},{"zip":"94539","county":"Alameda"},{"zip":"94540","county":"Alameda"},{"zip":"94541","county":"Alameda"},{"zip":"94542","county":"Alameda"},{"zip":"94543","county":"Alameda"},{"zip":"94544","county":"Alameda"},{"zip":"94545","county":"Alameda"},{"zip":"94546","county":"Alameda"},{"zip":"94547","county":"Contra Costa"},{"zip":"94548","county":"Contra Costa"},{"zip":"94549","county":"Contra Costa"},{"zip":"94550","county":"Alameda"},{"zip":"94551","county":"Alameda"},{"zip":"94552","county":"Alameda"},{"zip":"94553","county":"Contra Costa"},{"zip":"94555","county":"Alameda"},{"zip":"94556","county":"Contra Costa"},{"zip":"94557","county":"Alameda"},{"zip":"94558","county":"Napa"},{"zip":"94559","county":"Napa"},{"zip":"94560","county":"Alameda"},{"zip":"94561","county":"Contra Costa"},{"zip":"94562","county":"Napa"},{"zip":"94563","county":"Contra Costa"},{"zip":"94564","county":"Contra Costa"},{"zip":"94565","county":"Contra Costa"},{"zip":"94566","county":"Alameda"},{"zip":"94567","county":"Napa"},{"zip":"94568","county":"Alameda"},{"zip":"94569","county":"Contra Costa"},{"zip":"94570","county":"Contra Costa"},{"zip":"94571","county":"Solano"},{"zip":"94572","county":"Contra Costa"},{"zip":"94573","county":"Napa"},{"zip":"94574","county":"Napa"},{"zip":"94575","county":"Contra Costa"},{"zip":"94576","county":"Napa"},{"zip":"94577","county":"Alameda"},{"zip":"94578","county":"Alameda"},{"zip":"94579","county":"Alameda"},{"zip":"94580","county":"Alameda"},{"zip":"94581","county":"Napa"},{"zip":"94582","county":"Contra Costa"},{"zip":"94583","county":"Contra Costa"},{"zip":"94585","county":"Solano"},{"zip":"94586","county":"Alameda"},{"zip":"94587","county":"Alameda"},{"zip":"94588","county":"Alameda"},{"zip":"94589","county":"Solano"},{"zip":"94590","county":"Solano"},{"zip":"94591","county":"Solano"},{"zip":"94592","county":"Solano"},{"zip":"94595","county":"Contra Costa"},{"zip":"94596","county":"Contra Costa"},{"zip":"94597","county":"Contra Costa"},{"zip":"94598","county":"Contra Costa"},{"zip":"94599","county":"Napa"},{"zip":"94601","county":"Alameda"},{"zip":"94602","county":"Alameda"},{"zip":"94603","county":"Alameda"},{"zip":"94604","county":"Alameda"},{"zip":"94605","county":"Alameda"},{"zip":"94606","county":"Alameda"},{"zip":"94607","county":"Alameda"},{"zip":"94608","county":"Alameda"},{"zip":"94609","county":"Alameda"},{"zip":"94610","county":"Alameda"},{"zip":"94611","county":"Alameda"},{"zip":"94612","county":"Alameda"},{"zip":"94613","county":"Alameda"},{"zip":"94614","county":"Alameda"},{"zip":"94615","county":"Alameda"},{"zip":"94617","county":"Alameda"},{"zip":"94618","county":"Alameda"},{"zip":"94619","county":"Alameda"},{"zip":"94620","county":"Alameda"},{"zip":"94621","county":"Alameda"},{"zip":"94622","county":"Alameda"},{"zip":"94623","county":"Alameda"},{"zip":"94624","county":"Alameda"},{"zip":"94625","county":"Alameda"},{"zip":"94649","county":"Alameda"},{"zip":"94659","county":"Alameda"},{"zip":"94660","county":"Alameda"},{"zip":"94661","county":"Alameda"},{"zip":"94662","county":"Alameda"},{"zip":"94666","county":"Alameda"},{"zip":"94701","county":"Alameda"},{"zip":"94702","county":"Alameda"},{"zip":"94703","county":"Alameda"},{"zip":"94704","county":"Alameda"},{"zip":"94705","county":"Alameda"},{"zip":"94706","county":"Alameda"},{"zip":"94707","county":"Alameda"},{"zip":"94708","county":"Alameda"},{"zip":"94709","county":"Alameda"},{"zip":"94710","county":"Alameda"},{"zip":"94712","county":"Alameda"},{"zip":"94720","county":"Alameda"},{"zip":"94801","county":"Contra Costa"},{"zip":"94802","county":"Contra Costa"},{"zip":"94803","county":"Contra Costa"},{"zip":"94804","county":"Contra Costa"},{"zip":"94805","county":"Contra Costa"},{"zip":"94806","county":"Contra Costa"},{"zip":"94807","county":"Contra Costa"},{"zip":"94808","county":"Contra Costa"},{"zip":"94820","county":"Contra Costa"},{"zip":"94850","county":"Contra Costa"},{"zip":"94901","county":"Marin"},{"zip":"94903","county":"Marin"},{"zip":"94904","county":"Marin"},{"zip":"94912","county":"Marin"},{"zip":"94913","county":"Marin"},{"zip":"94914","county":"Marin"},{"zip":"94915","county":"Marin"},{"zip":"94920","county":"Marin"},{"zip":"94922","county":"Sonoma"},{"zip":"94923","county":"Sonoma"},{"zip":"94924","county":"Marin"},{"zip":"94925","county":"Marin"},{"zip":"94926","county":"Sonoma"},{"zip":"94927","county":"Sonoma"},{"zip":"94928","county":"Sonoma"},{"zip":"94929","county":"Marin"},{"zip":"94930","county":"Marin"},{"zip":"94931","county":"Sonoma"},{"zip":"94933","county":"Marin"},{"zip":"94937","county":"Marin"},{"zip":"94938","county":"Marin"},{"zip":"94939","county":"Marin"},{"zip":"94940","county":"Marin"},{"zip":"94941","county":"Marin"},{"zip":"94942","county":"Marin"},{"zip":"94945","county":"Marin"},{"zip":"94946","county":"Marin"},{"zip":"94947","county":"Marin"},{"zip":"94948","county":"Marin"},{"zip":"94949","county":"Marin"},{"zip":"94950","county":"Marin"},{"zip":"94951","county":"Sonoma"},{"zip":"94952","county":"Sonoma"},{"zip":"94953","county":"Sonoma"},{"zip":"94954","county":"Sonoma"},{"zip":"94955","county":"Sonoma"},{"zip":"94956","county":"Marin"},{"zip":"94957","county":"Marin"},{"zip":"94960","county":"Marin"},{"zip":"94963","county":"Marin"},{"zip":"94964","county":"Marin"},{"zip":"94965","county":"Marin"},{"zip":"94966","county":"Marin"},{"zip":"94970","county":"Marin"},{"zip":"94971","county":"Marin"},{"zip":"94972","county":"Sonoma"},{"zip":"94973","county":"Marin"},{"zip":"94974","county":"Marin"},{"zip":"94975","county":"Sonoma"},{"zip":"94976","county":"Marin"},{"zip":"94977","county":"Marin"},{"zip":"94978","county":"Marin"},{"zip":"94979","county":"Marin"},{"zip":"94998","county":"Marin"},{"zip":"94999","county":"Sonoma"},{"zip":"95001","county":"Santa Cruz"},{"zip":"95002","county":"Santa Clara"},{"zip":"95003","county":"Santa Cruz"},{"zip":"95004","county":"Monterey"},{"zip":"95005","county":"Santa Cruz"},{"zip":"95006","county":"Santa Cruz"},{"zip":"95007","county":"Santa Cruz"},{"zip":"95008","county":"Santa Clara"},{"zip":"95009","county":"Santa Clara"},{"zip":"95010","county":"Santa Cruz"},{"zip":"95011","county":"Santa Clara"},{"zip":"95012","county":"Monterey"},{"zip":"95013","county":"Santa Clara"},{"zip":"95014","county":"Santa Clara"},{"zip":"95015","county":"Santa Clara"},{"zip":"95017","county":"Santa Cruz"},{"zip":"95018","county":"Santa Cruz"},{"zip":"95019","county":"Santa Cruz"},{"zip":"95020","county":"Santa Clara"},{"zip":"95021","county":"Santa Clara"},{"zip":"95023","county":"San Benito"},{"zip":"95024","county":"San Benito"},{"zip":"95026","county":"Santa Clara"},{"zip":"95030","county":"Santa Clara"},{"zip":"95031","county":"Santa Clara"},{"zip":"95032","county":"Santa Clara"},{"zip":"95033","county":"Santa Cruz"},{"zip":"95035","county":"Santa Clara"},{"zip":"95036","county":"Santa Clara"},{"zip":"95037","county":"Santa Clara"},{"zip":"95038","county":"Santa Clara"},{"zip":"95039","county":"Monterey"},{"zip":"95041","county":"Santa Cruz"},{"zip":"95042","county":"Santa Clara"},{"zip":"95043","county":"San Benito"},{"zip":"95044","county":"Santa Clara"},{"zip":"95045","county":"San Benito"},{"zip":"95046","county":"Santa Clara"},{"zip":"95050","county":"Santa Clara"},{"zip":"95051","county":"Santa Clara"},{"zip":"95052","county":"Santa Clara"},{"zip":"95053","county":"Santa Clara"},{"zip":"95054","county":"Santa Clara"},{"zip":"95055","county":"Santa Clara"},{"zip":"95056","county":"Santa Clara"},{"zip":"95060","county":"Santa Cruz"},{"zip":"95061","county":"Santa Cruz"},{"zip":"95062","county":"Santa Cruz"},{"zip":"95063","county":"Santa Cruz"},{"zip":"95064","county":"Santa Cruz"},{"zip":"95065","county":"Santa Cruz"},{"zip":"95066","county":"Santa Cruz"},{"zip":"95067","county":"Santa Cruz"},{"zip":"95070","county":"Santa Clara"},{"zip":"95071","county":"Santa Clara"},{"zip":"95073","county":"Santa Cruz"},{"zip":"95075","county":"San Benito"},{"zip":"95076","county":"Santa Cruz"},{"zip":"95077","county":"Santa Cruz"},{"zip":"95101","county":"Santa Clara"},{"zip":"95103","county":"Santa Clara"},{"zip":"95106","county":"Santa Clara"},{"zip":"95108","county":"Santa Clara"},{"zip":"95109","county":"Santa Clara"},{"zip":"95110","county":"Santa Clara"},{"zip":"95111","county":"Santa Clara"},{"zip":"95112","county":"Santa Clara"},{"zip":"95113","county":"Santa Clara"},{"zip":"95115","county":"Santa Clara"},{"zip":"95116","county":"Santa Clara"},{"zip":"95117","county":"Santa Clara"},{"zip":"95118","county":"Santa Clara"},{"zip":"95119","county":"Santa Clara"},{"zip":"95120","county":"Santa Clara"},{"zip":"95121","county":"Santa Clara"},{"zip":"95122","county":"Santa Clara"},{"zip":"95123","county":"Santa Clara"},{"zip":"95124","county":"Santa Clara"},{"zip":"95125","county":"Santa Clara"},{"zip":"95126","county":"Santa Clara"},{"zip":"95127","county":"Santa Clara"},{"zip":"95128","county":"Santa Clara"},{"zip":"95129","county":"Santa Clara"},{"zip":"95130","county":"Santa Clara"},{"zip":"95131","county":"Santa Clara"},{"zip":"95132","county":"Santa Clara"},{"zip":"95133","county":"Santa Clara"},{"zip":"95134","county":"Santa Clara"},{"zip":"95135","county":"Santa Clara"},{"zip":"95136","county":"Santa Clara"},{"zip":"95138","county":"Santa Clara"},{"zip":"95139","county":"Santa Clara"},{"zip":"95140","county":"Santa Clara"},{"zip":"95141","county":"Santa Clara"},{"zip":"95148","county":"Santa Clara"},{"zip":"95150","county":"Santa Clara"},{"zip":"95151","county":"Santa Clara"},{"zip":"95152","county":"Santa Clara"},{"zip":"95153","county":"Santa Clara"},{"zip":"95154","county":"Santa Clara"},{"zip":"95155","county":"Santa Clara"},{"zip":"95156","county":"Santa Clara"},{"zip":"95157","county":"Santa Clara"},{"zip":"95158","county":"Santa Clara"},{"zip":"95159","county":"Santa Clara"},{"zip":"95160","county":"Santa Clara"},{"zip":"95161","county":"Santa Clara"},{"zip":"95164","county":"Santa Clara"},{"zip":"95170","county":"Santa Clara"},{"zip":"95172","county":"Santa Clara"},{"zip":"95173","county":"Santa Clara"},{"zip":"95190","county":"Santa Clara"},{"zip":"95191","county":"Santa Clara"},{"zip":"95192","county":"Santa Clara"},{"zip":"95193","county":"Santa Clara"},{"zip":"95194","county":"Santa Clara"},{"zip":"95196","county":"Santa Clara"},{"zip":"95201","county":"San Joaquin"},{"zip":"95202","county":"San Joaquin"},{"zip":"95203","county":"San Joaquin"},{"zip":"95204","county":"San Joaquin"},{"zip":"95205","county":"San Joaquin"},{"zip":"95206","county":"San Joaquin"},{"zip":"95207","county":"San Joaquin"},{"zip":"95208","county":"San Joaquin"},{"zip":"95209","county":"San Joaquin"},{"zip":"95210","county":"San Joaquin"},{"zip":"95211","county":"San Joaquin"},{"zip":"95212","county":"San Joaquin"},{"zip":"95213","county":"San Joaquin"},{"zip":"95215","county":"San Joaquin"},{"zip":"95219","county":"San Joaquin"},{"zip":"95220","county":"San Joaquin"},{"zip":"95221","county":"Calaveras"},{"zip":"95222","county":"Calaveras"},{"zip":"95223","county":"Calaveras"},{"zip":"95224","county":"Calaveras"},{"zip":"95225","county":"Calaveras"},{"zip":"95226","county":"Calaveras"},{"zip":"95227","county":"San Joaquin"},{"zip":"95228","county":"Calaveras"},{"zip":"95229","county":"Calaveras"},{"zip":"95230","county":"San Joaquin"},{"zip":"95231","county":"San Joaquin"},{"zip":"95232","county":"Calaveras"},{"zip":"95233","county":"Calaveras"},{"zip":"95234","county":"San Joaquin"},{"zip":"95236","county":"San Joaquin"},{"zip":"95237","county":"San Joaquin"},{"zip":"95240","county":"San Joaquin"},{"zip":"95241","county":"San Joaquin"},{"zip":"95242","county":"San Joaquin"},{"zip":"95245","county":"Calaveras"},{"zip":"95246","county":"Calaveras"},{"zip":"95247","county":"Calaveras"},{"zip":"95248","county":"Calaveras"},{"zip":"95249","county":"Calaveras"},{"zip":"95250","county":"Calaveras"},{"zip":"95251","county":"Calaveras"},{"zip":"95252","county":"Calaveras"},{"zip":"95253","county":"San Joaquin"},{"zip":"95254","county":"Calaveras"},{"zip":"95255","county":"Calaveras"},{"zip":"95257","county":"Calaveras"},{"zip":"95258","county":"San Joaquin"},{"zip":"95267","county":"San Joaquin"},{"zip":"95269","county":"San Joaquin"},{"zip":"95296","county":"San Joaquin"},{"zip":"95297","county":"San Joaquin"},{"zip":"95301","county":"Merced"},{"zip":"95303","county":"Merced"},{"zip":"95304","county":"San Joaquin"},{"zip":"95305","county":"Tuolumne"},{"zip":"95306","county":"Mariposa"},{"zip":"95307","county":"Stanislaus"},{"zip":"95309","county":"Tuolumne"},{"zip":"95310","county":"Tuolumne"},{"zip":"95311","county":"Mariposa"},{"zip":"95312","county":"Merced"},{"zip":"95313","county":"Stanislaus"},{"zip":"95314","county":"Tuolumne"},{"zip":"95315","county":"Merced"},{"zip":"95316","county":"Stanislaus"},{"zip":"95317","county":"Merced"},{"zip":"95318","county":"Mariposa"},{"zip":"95319","county":"Stanislaus"},{"zip":"95320","county":"San Joaquin"},{"zip":"95321","county":"Tuolumne"},{"zip":"95322","county":"Merced"},{"zip":"95323","county":"Stanislaus"},{"zip":"95324","county":"Merced"},{"zip":"95325","county":"Mariposa"},{"zip":"95326","county":"Stanislaus"},{"zip":"95327","county":"Tuolumne"},{"zip":"95328","county":"Stanislaus"},{"zip":"95329","county":"Stanislaus"},{"zip":"95330","county":"San Joaquin"},{"zip":"95333","county":"Merced"},{"zip":"95334","county":"Merced"},{"zip":"95335","county":"Tuolumne"},{"zip":"95336","county":"San Joaquin"},{"zip":"95337","county":"San Joaquin"},{"zip":"95338","county":"Mariposa"},{"zip":"95340","county":"Merced"},{"zip":"95341","county":"Merced"},{"zip":"95343","county":"Merced"},{"zip":"95344","county":"Merced"},{"zip":"95345","county":"Mariposa"},{"zip":"95346","county":"Tuolumne"},{"zip":"95347","county":"Tuolumne"},{"zip":"95348","county":"Merced"},{"zip":"95350","county":"Stanislaus"},{"zip":"95351","county":"Stanislaus"},{"zip":"95352","county":"Stanislaus"},{"zip":"95353","county":"Stanislaus"},{"zip":"95354","county":"Stanislaus"},{"zip":"95355","county":"Stanislaus"},{"zip":"95356","county":"Stanislaus"},{"zip":"95357","county":"Stanislaus"},{"zip":"95358","county":"Stanislaus"},{"zip":"95360","county":"Stanislaus"},{"zip":"95361","county":"Stanislaus"},{"zip":"95363","county":"Stanislaus"},{"zip":"95364","county":"Tuolumne"},{"zip":"95365","county":"Merced"},{"zip":"95366","county":"San Joaquin"},{"zip":"95367","county":"Stanislaus"},{"zip":"95368","county":"Stanislaus"},{"zip":"95369","county":"Merced"},{"zip":"95370","county":"Tuolumne"},{"zip":"95372","county":"Tuolumne"},{"zip":"95373","county":"Tuolumne"},{"zip":"95374","county":"Merced"},{"zip":"95375","county":"Tuolumne"},{"zip":"95376","county":"San Joaquin"},{"zip":"95377","county":"San Joaquin"},{"zip":"95378","county":"San Joaquin"},{"zip":"95379","county":"Tuolumne"},{"zip":"95380","county":"Stanislaus"},{"zip":"95381","county":"Stanislaus"},{"zip":"95382","county":"Stanislaus"},{"zip":"95383","county":"Tuolumne"},{"zip":"95385","county":"San Joaquin"},{"zip":"95386","county":"Stanislaus"},{"zip":"95387","county":"Stanislaus"},{"zip":"95388","county":"Merced"},{"zip":"95389","county":"Mariposa"},{"zip":"95391","county":"San Joaquin"},{"zip":"95397","county":"Stanislaus"},{"zip":"95401","county":"Sonoma"},{"zip":"95402","county":"Sonoma"},{"zip":"95403","county":"Sonoma"},{"zip":"95404","county":"Sonoma"},{"zip":"95405","county":"Sonoma"},{"zip":"95406","county":"Sonoma"},{"zip":"95407","county":"Sonoma"},{"zip":"95408","county":"Sonoma"},{"zip":"95409","county":"Sonoma"},{"zip":"95410","county":"Mendocino"},{"zip":"95412","county":"Sonoma"},{"zip":"95415","county":"Mendocino"},{"zip":"95416","county":"Sonoma"},{"zip":"95417","county":"Mendocino"},{"zip":"95418","county":"Mendocino"},{"zip":"95419","county":"Sonoma"},{"zip":"95420","county":"Mendocino"},{"zip":"95421","county":"Sonoma"},{"zip":"95422","county":"Lake"},{"zip":"95423","county":"Lake"},{"zip":"95424","county":"Lake"},{"zip":"95425","county":"Sonoma"},{"zip":"95426","county":"Lake"},{"zip":"95427","county":"Mendocino"},{"zip":"95428","county":"Mendocino"},{"zip":"95429","county":"Mendocino"},{"zip":"95430","county":"Sonoma"},{"zip":"95431","county":"Sonoma"},{"zip":"95432","county":"Mendocino"},{"zip":"95433","county":"Sonoma"},{"zip":"95435","county":"Lake"},{"zip":"95436","county":"Sonoma"},{"zip":"95437","county":"Mendocino"},{"zip":"95439","county":"Sonoma"},{"zip":"95441","county":"Sonoma"},{"zip":"95442","county":"Sonoma"},{"zip":"95443","county":"Lake"},{"zip":"95444","county":"Sonoma"},{"zip":"95445","county":"Mendocino"},{"zip":"95446","county":"Sonoma"},{"zip":"95448","county":"Sonoma"},{"zip":"95449","county":"Mendocino"},{"zip":"95450","county":"Sonoma"},{"zip":"95451","county":"Lake"},{"zip":"95452","county":"Sonoma"},{"zip":"95453","county":"Lake"},{"zip":"95454","county":"Mendocino"},{"zip":"95456","county":"Mendocino"},{"zip":"95457","county":"Lake"},{"zip":"95458","county":"Lake"},{"zip":"95459","county":"Mendocino"},{"zip":"95460","county":"Mendocino"},{"zip":"95461","county":"Lake"},{"zip":"95462","county":"Sonoma"},{"zip":"95463","county":"Mendocino"},{"zip":"95464","county":"Lake"},{"zip":"95465","county":"Sonoma"},{"zip":"95466","county":"Mendocino"},{"zip":"95467","county":"Lake"},{"zip":"95468","county":"Mendocino"},{"zip":"95469","county":"Mendocino"},{"zip":"95470","county":"Mendocino"},{"zip":"95471","county":"Sonoma"},{"zip":"95472","county":"Sonoma"},{"zip":"95473","county":"Sonoma"},{"zip":"95476","county":"Sonoma"},{"zip":"95480","county":"Sonoma"},{"zip":"95481","county":"Mendocino"},{"zip":"95482","county":"Mendocino"},{"zip":"95485","county":"Lake"},{"zip":"95486","county":"Sonoma"},{"zip":"95487","county":"Sonoma"},{"zip":"95488","county":"Mendocino"},{"zip":"95490","county":"Mendocino"},{"zip":"95492","county":"Sonoma"},{"zip":"95493","county":"Lake"},{"zip":"95494","county":"Mendocino"},{"zip":"95497","county":"Sonoma"},{"zip":"95501","county":"Humboldt"},{"zip":"95502","county":"Humboldt"},{"zip":"95503","county":"Humboldt"},{"zip":"95511","county":"Humboldt"},{"zip":"95514","county":"Humboldt"},{"zip":"95518","county":"Humboldt"},{"zip":"95519","county":"Humboldt"},{"zip":"95521","county":"Humboldt"},{"zip":"95524","county":"Humboldt"},{"zip":"95525","county":"Humboldt"},{"zip":"95526","county":"Humboldt"},{"zip":"95527","county":"Trinity"},{"zip":"95528","county":"Humboldt"},{"zip":"95531","county":"Del Norte"},{"zip":"95532","county":"Del Norte"},{"zip":"95534","county":"Humboldt"},{"zip":"95536","county":"Humboldt"},{"zip":"95537","county":"Humboldt"},{"zip":"95538","county":"Del Norte"},{"zip":"95540","county":"Humboldt"},{"zip":"95542","county":"Humboldt"},{"zip":"95543","county":"Del Norte"},{"zip":"95545","county":"Humboldt"},{"zip":"95546","county":"Humboldt"},{"zip":"95547","county":"Humboldt"},{"zip":"95548","county":"Del Norte"},{"zip":"95549","county":"Humboldt"},{"zip":"95550","county":"Humboldt"},{"zip":"95551","county":"Humboldt"},{"zip":"95552","county":"Trinity"},{"zip":"95553","county":"Humboldt"},{"zip":"95554","county":"Humboldt"},{"zip":"95555","county":"Humboldt"},{"zip":"95556","county":"Humboldt"},{"zip":"95558","county":"Humboldt"},{"zip":"95559","county":"Humboldt"},{"zip":"95560","county":"Humboldt"},{"zip":"95562","county":"Humboldt"},{"zip":"95563","county":"Trinity"},{"zip":"95564","county":"Humboldt"},{"zip":"95565","county":"Humboldt"},{"zip":"95567","county":"Del Norte"},{"zip":"95568","county":"Siskiyou"},{"zip":"95569","county":"Humboldt"},{"zip":"95570","county":"Humboldt"},{"zip":"95571","county":"Humboldt"},{"zip":"95573","county":"Humboldt"},{"zip":"95585","county":"Mendocino"},{"zip":"95587","county":"Mendocino"},{"zip":"95589","county":"Humboldt"},{"zip":"95595","county":"Trinity"},{"zip":"95601","county":"Amador"},{"zip":"95602","county":"Placer"},{"zip":"95603","county":"Placer"},{"zip":"95604","county":"Placer"},{"zip":"95605","county":"Yolo"},{"zip":"95606","county":"Yolo"},{"zip":"95607","county":"Yolo"},{"zip":"95608","county":"Sacramento"},{"zip":"95609","county":"Sacramento"},{"zip":"95610","county":"Sacramento"},{"zip":"95611","county":"Sacramento"},{"zip":"95612","county":"Yolo"},{"zip":"95613","county":"El Dorado"},{"zip":"95614","county":"El Dorado"},{"zip":"95615","county":"Sacramento"},{"zip":"95616","county":"Yolo"},{"zip":"95617","county":"Yolo"},{"zip":"95618","county":"Yolo"},{"zip":"95619","county":"El Dorado"},{"zip":"95620","county":"Solano"},{"zip":"95621","county":"Sacramento"},{"zip":"95623","county":"El Dorado"},{"zip":"95624","county":"Sacramento"},{"zip":"95625","county":"Solano"},{"zip":"95626","county":"Sacramento"},{"zip":"95627","county":"Yolo"},{"zip":"95628","county":"Sacramento"},{"zip":"95629","county":"Amador"},{"zip":"95630","county":"Sacramento"},{"zip":"95631","county":"Placer"},{"zip":"95632","county":"Sacramento"},{"zip":"95633","county":"El Dorado"},{"zip":"95634","county":"El Dorado"},{"zip":"95635","county":"El Dorado"},{"zip":"95636","county":"El Dorado"},{"zip":"95637","county":"Yolo"},{"zip":"95638","county":"Sacramento"},{"zip":"95639","county":"Sacramento"},{"zip":"95640","county":"Amador"},{"zip":"95641","county":"Sacramento"},{"zip":"95642","county":"Amador"},{"zip":"95644","county":"Amador"},{"zip":"95645","county":"Yolo"},{"zip":"95646","county":"Alpine"},{"zip":"95648","county":"Placer"},{"zip":"95650","county":"Placer"},{"zip":"95651","county":"El Dorado"},{"zip":"95652","county":"Sacramento"},{"zip":"95653","county":"Yolo"},{"zip":"95654","county":"Amador"},{"zip":"95655","county":"Sacramento"},{"zip":"95656","county":"El Dorado"},{"zip":"95658","county":"Placer"},{"zip":"95659","county":"Sutter"},{"zip":"95660","county":"Sacramento"},{"zip":"95661","county":"Placer"},{"zip":"95662","county":"Sacramento"},{"zip":"95663","county":"Placer"},{"zip":"95664","county":"El Dorado"},{"zip":"95665","county":"Amador"},{"zip":"95666","county":"Amador"},{"zip":"95667","county":"El Dorado"},{"zip":"95668","county":"Sutter"},{"zip":"95669","county":"Amador"},{"zip":"95670","county":"Sacramento"},{"zip":"95671","county":"Sacramento"},{"zip":"95672","county":"El Dorado"},{"zip":"95673","county":"Sacramento"},{"zip":"95674","county":"Sutter"},{"zip":"95675","county":"Amador"},{"zip":"95676","county":"Sutter"},{"zip":"95677","county":"Placer"},{"zip":"95678","county":"Placer"},{"zip":"95679","county":"Yolo"},{"zip":"95680","county":"Sacramento"},{"zip":"95681","county":"Placer"},{"zip":"95682","county":"El Dorado"},{"zip":"95683","county":"Sacramento"},{"zip":"95684","county":"El Dorado"},{"zip":"95685","county":"Amador"},{"zip":"95686","county":"San Joaquin"},{"zip":"95687","county":"Solano"},{"zip":"95688","county":"Solano"},{"zip":"95689","county":"Amador"},{"zip":"95690","county":"Sacramento"},{"zip":"95691","county":"Yolo"},{"zip":"95692","county":"Yuba"},{"zip":"95693","county":"Sacramento"},{"zip":"95694","county":"Yolo"},{"zip":"95695","county":"Yolo"},{"zip":"95696","county":"Solano"},{"zip":"95697","county":"Yolo"},{"zip":"95698","county":"Yolo"},{"zip":"95699","county":"Amador"},{"zip":"95701","county":"Placer"},{"zip":"95703","county":"Placer"},{"zip":"95709","county":"El Dorado"},{"zip":"95712","county":"Nevada"},{"zip":"95713","county":"Placer"},{"zip":"95714","county":"Placer"},{"zip":"95715","county":"Placer"},{"zip":"95717","county":"Placer"},{"zip":"95720","county":"El Dorado"},{"zip":"95721","county":"El Dorado"},{"zip":"95722","county":"Placer"},{"zip":"95724","county":"Nevada"},{"zip":"95726","county":"El Dorado"},{"zip":"95728","county":"Nevada"},{"zip":"95735","county":"El Dorado"},{"zip":"95736","county":"Placer"},{"zip":"95741","county":"Sacramento"},{"zip":"95742","county":"Sacramento"},{"zip":"95746","county":"Placer"},{"zip":"95747","county":"Placer"},{"zip":"95757","county":"Sacramento"},{"zip":"95758","county":"Sacramento"},{"zip":"95759","county":"Sacramento"},{"zip":"95762","county":"El Dorado"},{"zip":"95763","county":"Sacramento"},{"zip":"95765","county":"Placer"},{"zip":"95776","county":"Yolo"},{"zip":"95798","county":"Yolo"},{"zip":"95799","county":"Yolo"},{"zip":"95812","county":"Sacramento"},{"zip":"95813","county":"Sacramento"},{"zip":"95814","county":"Sacramento"},{"zip":"95815","county":"Sacramento"},{"zip":"95816","county":"Sacramento"},{"zip":"95817","county":"Sacramento"},{"zip":"95818","county":"Sacramento"},{"zip":"95819","county":"Sacramento"},{"zip":"95820","county":"Sacramento"},{"zip":"95821","county":"Sacramento"},{"zip":"95822","county":"Sacramento"},{"zip":"95823","county":"Sacramento"},{"zip":"95824","county":"Sacramento"},{"zip":"95825","county":"Sacramento"},{"zip":"95826","county":"Sacramento"},{"zip":"95827","county":"Sacramento"},{"zip":"95828","county":"Sacramento"},{"zip":"95829","county":"Sacramento"},{"zip":"95830","county":"Sacramento"},{"zip":"95831","county":"Sacramento"},{"zip":"95832","county":"Sacramento"},{"zip":"95833","county":"Sacramento"},{"zip":"95834","county":"Sacramento"},{"zip":"95835","county":"Sacramento"},{"zip":"95836","county":"Sacramento"},{"zip":"95837","county":"Sacramento"},{"zip":"95838","county":"Sacramento"},{"zip":"95840","county":"Sacramento"},{"zip":"95841","county":"Sacramento"},{"zip":"95842","county":"Sacramento"},{"zip":"95843","county":"Sacramento"},{"zip":"95851","county":"Sacramento"},{"zip":"95852","county":"Sacramento"},{"zip":"95853","county":"Sacramento"},{"zip":"95860","county":"Sacramento"},{"zip":"95864","county":"Sacramento"},{"zip":"95865","county":"Sacramento"},{"zip":"95866","county":"Sacramento"},{"zip":"95867","county":"Sacramento"},{"zip":"95887","county":"Sacramento"},{"zip":"95894","county":"Sacramento"},{"zip":"95899","county":"Sacramento"},{"zip":"95901","county":"Yuba"},{"zip":"95903","county":"Yuba"},{"zip":"95910","county":"Sierra"},{"zip":"95912","county":"Colusa"},{"zip":"95913","county":"Glenn"},{"zip":"95914","county":"Butte"},{"zip":"95915","county":"Plumas"},{"zip":"95916","county":"Butte"},{"zip":"95917","county":"Butte"},{"zip":"95918","county":"Yuba"},{"zip":"95919","county":"Yuba"},{"zip":"95920","county":"Glenn"},{"zip":"95922","county":"Yuba"},{"zip":"95923","county":"Plumas"},{"zip":"95924","county":"Nevada"},{"zip":"95925","county":"Yuba"},{"zip":"95926","county":"Butte"},{"zip":"95927","county":"Butte"},{"zip":"95928","county":"Butte"},{"zip":"95929","county":"Butte"},{"zip":"95930","county":"Butte"},{"zip":"95932","county":"Colusa"},{"zip":"95934","county":"Plumas"},{"zip":"95935","county":"Yuba"},{"zip":"95936","county":"Sierra"},{"zip":"95937","county":"Yolo"},{"zip":"95938","county":"Butte"},{"zip":"95939","county":"Glenn"},{"zip":"95940","county":"Butte"},{"zip":"95941","county":"Butte"},{"zip":"95942","county":"Butte"},{"zip":"95943","county":"Glenn"},{"zip":"95944","county":"Sierra"},{"zip":"95945","county":"Nevada"},{"zip":"95946","county":"Nevada"},{"zip":"95947","county":"Plumas"},{"zip":"95948","county":"Butte"},{"zip":"95949","county":"Nevada"},{"zip":"95950","county":"Colusa"},{"zip":"95951","county":"Glenn"},{"zip":"95953","county":"Sutter"},{"zip":"95954","county":"Butte"},{"zip":"95955","county":"Colusa"},{"zip":"95956","county":"Plumas"},{"zip":"95957","county":"Sutter"},{"zip":"95958","county":"Butte"},{"zip":"95959","county":"Nevada"},{"zip":"95960","county":"Nevada"},{"zip":"95961","county":"Yuba"},{"zip":"95962","county":"Yuba"},{"zip":"95963","county":"Glenn"},{"zip":"95965","county":"Butte"},{"zip":"95966","county":"Butte"},{"zip":"95967","county":"Butte"},{"zip":"95968","county":"Butte"},{"zip":"95969","county":"Butte"},{"zip":"95970","county":"Colusa"},{"zip":"95971","county":"Plumas"},{"zip":"95972","county":"Yuba"},{"zip":"95973","county":"Butte"},{"zip":"95974","county":"Butte"},{"zip":"95975","county":"Nevada"},{"zip":"95976","county":"Butte"},{"zip":"95977","county":"Nevada"},{"zip":"95978","county":"Butte"},{"zip":"95979","county":"Colusa"},{"zip":"95980","county":"Plumas"},{"zip":"95981","county":"Yuba"},{"zip":"95982","county":"Sutter"},{"zip":"95983","county":"Plumas"},{"zip":"95984","county":"Plumas"},{"zip":"95986","county":"Nevada"},{"zip":"95987","county":"Colusa"},{"zip":"95988","county":"Glenn"},{"zip":"95991","county":"Sutter"},{"zip":"95992","county":"Sutter"},{"zip":"95993","county":"Sutter"},{"zip":"96001","county":"Shasta"},{"zip":"96002","county":"Shasta"},{"zip":"96003","county":"Shasta"},{"zip":"96006","county":"Modoc"},{"zip":"96007","county":"Shasta"},{"zip":"96008","county":"Shasta"},{"zip":"96009","county":"Lassen"},{"zip":"96010","county":"Trinity"},{"zip":"96011","county":"Shasta"},{"zip":"96013","county":"Shasta"},{"zip":"96014","county":"Siskiyou"},{"zip":"96015","county":"Modoc"},{"zip":"96016","county":"Shasta"},{"zip":"96017","county":"Shasta"},{"zip":"96019","county":"Shasta"},{"zip":"96020","county":"Plumas"},{"zip":"96021","county":"Tehama"},{"zip":"96022","county":"Shasta"},{"zip":"96023","county":"Siskiyou"},{"zip":"96024","county":"Trinity"},{"zip":"96025","county":"Siskiyou"},{"zip":"96027","county":"Siskiyou"},{"zip":"96028","county":"Shasta"},{"zip":"96029","county":"Tehama"},{"zip":"96031","county":"Siskiyou"},{"zip":"96032","county":"Siskiyou"},{"zip":"96033","county":"Shasta"},{"zip":"96034","county":"Siskiyou"},{"zip":"96035","county":"Tehama"},{"zip":"96037","county":"Siskiyou"},{"zip":"96038","county":"Siskiyou"},{"zip":"96039","county":"Siskiyou"},{"zip":"96040","county":"Shasta"},{"zip":"96041","county":"Trinity"},{"zip":"96044","county":"Siskiyou"},{"zip":"96046","county":"Trinity"},{"zip":"96047","county":"Shasta"},{"zip":"96048","county":"Trinity"},{"zip":"96049","county":"Shasta"},{"zip":"96050","county":"Siskiyou"},{"zip":"96051","county":"Shasta"},{"zip":"96052","county":"Trinity"},{"zip":"96054","county":"Modoc"},{"zip":"96055","county":"Tehama"},{"zip":"96056","county":"Lassen"},{"zip":"96057","county":"Siskiyou"},{"zip":"96058","county":"Siskiyou"},{"zip":"96059","county":"Tehama"},{"zip":"96061","county":"Tehama"},{"zip":"96062","county":"Shasta"},{"zip":"96063","county":"Tehama"},{"zip":"96064","county":"Siskiyou"},{"zip":"96065","county":"Shasta"},{"zip":"96067","county":"Siskiyou"},{"zip":"96068","county":"Lassen"},{"zip":"96069","county":"Shasta"},{"zip":"96070","county":"Shasta"},{"zip":"96071","county":"Shasta"},{"zip":"96073","county":"Shasta"},{"zip":"96074","county":"Tehama"},{"zip":"96075","county":"Tehama"},{"zip":"96076","county":"Shasta"},{"zip":"96078","county":"Tehama"},{"zip":"96079","county":"Shasta"},{"zip":"96080","county":"Tehama"},{"zip":"96084","county":"Shasta"},{"zip":"96085","county":"Siskiyou"},{"zip":"96086","county":"Siskiyou"},{"zip":"96087","county":"Shasta"},{"zip":"96088","county":"Shasta"},{"zip":"96089","county":"Shasta"},{"zip":"96090","county":"Tehama"},{"zip":"96091","county":"Trinity"},{"zip":"96092","county":"Tehama"},{"zip":"96093","county":"Trinity"},{"zip":"96094","county":"Siskiyou"},{"zip":"96095","county":"Shasta"},{"zip":"96096","county":"Shasta"},{"zip":"96097","county":"Siskiyou"},{"zip":"96099","county":"Shasta"},{"zip":"96101","county":"Modoc"},{"zip":"96103","county":"Plumas"},{"zip":"96104","county":"Modoc"},{"zip":"96105","county":"Plumas"},{"zip":"96106","county":"Plumas"},{"zip":"96107","county":"Mono"},{"zip":"96108","county":"Modoc"},{"zip":"96109","county":"Lassen"},{"zip":"96110","county":"Modoc"},{"zip":"96111","county":"Nevada"},{"zip":"96112","county":"Modoc"},{"zip":"96113","county":"Lassen"},{"zip":"96114","county":"Lassen"},{"zip":"96115","county":"Modoc"},{"zip":"96116","county":"Modoc"},{"zip":"96117","county":"Lassen"},{"zip":"96118","county":"Sierra"},{"zip":"96119","county":"Lassen"},{"zip":"96120","county":"Alpine"},{"zip":"96121","county":"Lassen"},{"zip":"96122","county":"Plumas"},{"zip":"96123","county":"Lassen"},{"zip":"96124","county":"Sierra"},{"zip":"96125","county":"Sierra"},{"zip":"96126","county":"Sierra"},{"zip":"96127","county":"Lassen"},{"zip":"96128","county":"Lassen"},{"zip":"96129","county":"Plumas"},{"zip":"96130","county":"Lassen"},{"zip":"96132","county":"Lassen"},{"zip":"96133","county":"Mono"},{"zip":"96134","county":"Siskiyou"},{"zip":"96135","county":"Plumas"},{"zip":"96136","county":"Lassen"},{"zip":"96137","county":"Lassen"},{"zip":"96140","county":"Placer"},{"zip":"96141","county":"Placer"},{"zip":"96142","county":"El Dorado"},{"zip":"96143","county":"Placer"},{"zip":"96145","county":"Placer"},{"zip":"96146","county":"Placer"},{"zip":"96148","county":"Placer"},{"zip":"96150","county":"El Dorado"},{"zip":"96151","county":"El Dorado"},{"zip":"96152","county":"El Dorado"},{"zip":"96154","county":"El Dorado"},{"zip":"96155","county":"El Dorado"},{"zip":"96156","county":"El Dorado"},{"zip":"96157","county":"El Dorado"},{"zip":"96158","county":"El Dorado"},{"zip":"96160","county":"Nevada"},{"zip":"96161","county":"Nevada"},{"zip":"96162","county":"Nevada"},{},{"zip":"136 KB","county":"160 KB"},{"zip":"16 KB","county":"30 KB"},{"zip":"2 KB","county":"8 KB"}]