{							"@context": "http://schema.org",							"@type": "LocalBusiness",							"address": {							"@type":"PostalAddress",							"streetAddress":"1345 Ocean Avenue",							"addressLocality":"San Francisco",							"addressRegion":"CA",							"postalCode": "94112"														},							"name": "Ingleside Community Center",							"telephone":"(415) 586-4765",							"image": "",							"description": "Provides a food pantry.  Serves San Francisco County (94112, 94132) <br /><br />Pantry Hours: <br />Thursday <br />10:30am<br />(Closed on all major holidays)"							}